Workbook

Sheet README
A1: Regression Skill Test Workbook
A2: Version | B2: Solved regression feature test fixture
A3: Purpose | B3: Test whether the Excel skill selects, executes, explains, and classifies regression models for common business questions.
A4: How to use | B4: Runed each prompt from Prompt_Bank against the matching worksheet.
A5: Required output 1 | B5: A nine-point Regression Analysis Results section on the same worksheet as the source data.
A6: Required output 2 | B6: A new Regression_Model_Summary worksheet with model statistics, coefficients, predictions, residuals, diagnostics, and the three most relevant predictors.
A7: Classification | B7: The main report must end with Ready for decision support, Use with caution, or Do not rely on this model yet, using green, yellow, or red formatting.
A8: Interpretation standard | B8: Connect statistical outputs to the business question, distinguish association from causation, and avoid overwhelming the business user with unnecessary detail.
A9: Test coverage | B9: Simple OLS, multiple OLS, influential outlier, multicollinearity, nonlinear pattern, binary outcome, and time leakage.
A10: Solved copy | B10: TESTED
A12: Advanced / Higher-Risk Tests | B12: The final five test sheets are either still unsolved or intentionally contain material data/model risks. Their results require additional diagnostics or a different method before decision use.
A13: Outlier_Influence | B13: Analyzed, but higher risk: one high-leverage enterprise campaign dominates the regression and materially changes the slope. A pooled model should not be used across standard and enterprise campaigns.
A14: Multicollinearity | B14: Analyzed, but higher risk: paid media spend, reach, and brand impressions are near-duplicate predictors. Overall prediction is strong, but individual coefficients are unstable and should not be interpreted separately.
... A18: Overall caution | B18: These sheets are diagnostic stress tests rather than clean regression examples. Do not rely on high R-squared alone; method suitability, leakage, nonlinear shape, influential observations, and coefficient stability must be resolved first.

Sheet Prompt_Bank
A1: Regression Test Prompt Bank
A2: Use the prompt with the corresponding sheet. The workbook intentionally includes method-selection and diagnostic traps.
A6: Test ID | B6: Worksheet | C6: Prompt
A7: REG-01 | B7: Simple_Linear | C7: Estimate how monthly marketing spend is associated with sales.
A8: REG-02 | B8: Multiple_Regression | C8: Estimate monthly sales using marketing spend, average discount, seasonality index, and active sales representatives.
A9: REG-03 | B9: Outlier_Influence | C9: Evaluate whether marketing spend predicts revenue reliably when one enterprise campaign is much larger than the other observations. Compare results with and without the influential observation.
A10: REG-04 | B10: Multicollinearity | C10: Model sales using paid media spend, campaign reach, and brand impressions. Assess whether individual coefficients can be interpreted reliably.
A11: REG-05 | B11: Nonlinear_Risk | C11: Assess whether a straight-line regression is appropriate for forecasting sales response to marketing spend across the full investment range.
A12: REG-06 | B12: Binary_Outcome | C12: Predict customer churn from service tickets, tenure, and monthly spend. Decide whether ordinary linear regression is appropriate before modeling.
A13: REG-07 | B13: Time_Leakage | C13: Build a planning model for monthly sales using only information available before month end. Check whether every proposed predictor is valid at prediction time.

Sheet Answer_Key
A1: Regression Test Answer Key
A2: Use this sheet to assess method selection, interpretation, diagnostics, mandatory outputs, and model classification.
A6: Test ID | B6: Worksheet | C6: Expected method | D6: Expected interpretation or warning | E6: Expected classification
A7: REG-01 | B7: Simple_Linear | C7: Simple linear OLS | D7: A strong positive linear association supports planning, but the result is observational rather than causal. | E7: Ready for decision support
A8: REG-02 | B8: Multiple_Regression | C8: Multiple OLS | D8: Interpret each coefficient while holding the other predictors constant; surface the top three predictors in the technical summary. | E8: Ready for decision support
A9: REG-03 | B9: Outlier_Influence | C9: OLS sensitivity analysis | D9: The enterprise observation materially changes the fitted relationship; the skill should flag influence and avoid a confident decision-ready classification. | E9: Use with caution
A10: REG-04 | B10: Multicollinearity | C10: Multiple OLS with collinearity diagnostics | D10: The predictors contain heavily overlapping information. Overall fit may look strong while individual coefficients are unstable. | E10: Use with caution
A11: REG-05 | B11: Nonlinear_Risk | C11: Linearity assessment | D11: The data show diminishing returns. A single linear slope should not be treated as stable across the full range. | E11: Do not rely on this model yet
A12: REG-06 | B12: Binary_Outcome | C12: Method-selection gate | D12: Churn is binary, so ordinary linear regression is inappropriate. Recommend logistic regression instead. | E12: Do not rely on this model yet
A13: REG-07 | B13: Time_Leakage | C13: Prediction-time data audit | D13: Month-end sales adjustment is calculated after actual sales are known and creates look-ahead leakage. Remove it before fitting. | E13: Do not rely on this model yet

Sheet Simple_Linear
A1: Simple Linear Regression: Marketing Spend and Sales
A2: Unsolved test case. Run the regression skill against this sheet and retain both mandatory Excel outputs.
A3: Business question | B3: Can monthly marketing spend help estimate sales for planning purposes?
A4: Design note | B4: One continuous outcome and one continuous predictor with a strong linear pattern. Seasonality is supplied as context, not as a predictor for this test.
A6: Month | B6: Marketing Spend | C6: Sales | D6: Seasonality Context
A7: 45292 | B7: 12000 | C7: 103000 | D7: 3000
A8: 45323 | B8: 14650 | C8: 111198 | D8: -2500
A9: 45352 | B9: 15000 | C9: 115150 | D9: 1500
A10: 45383 | B10: 17850 | C10: 131478 | D10: 4200
A11: 45413 | B11: 19000 | C11: 128750 | D11: -1200
A12: 45444 | B12: 21650 | C12: 144548 | D12: 2000
A13: 45474 | B13: 22000 | C13: 144500 | D13: 3000
A14: 45505 | B14: 24850 | C14: 153528 | D14: -2500
A15: 45536 | B15: 26000 | C15: 160800 | D15: 1500
A16: 45566 | B16: 28650 | C16: 176298 | D16: 4200
A17: 45597 | B17: 29000 | C17: 170250 | D17: -1200
A18: 45627 | B18: 31850 | C18: 186878 | D18: 2000
... A30: 45992 | B30: 52850 | C30: 274028 | D30: 2000
A33: Regression Analysis Results
A35: Business question | B35: How is monthly marketing spend associated with same-month sales?
A36: Model used | B36: Simple linear regression with Sales as the continuous outcome and Marketing Spend as the numeric predictor. This estimates the change in sales associated with a change in spend.
A37: Data scope | B37: 24 monthly observations from Jan-2024 through Dec-2025; no rows excluded.
A38: Key driver | B38: ="Each additional $1,000 of monthly marketing spend is associated with approximately "&TEXT(Simple_Linear_Reg_Analysis!$B$33*1000,"$#,##0")&" higher same-month sales." -> Each additional $1,000 of monthly marketing spend is associated with approximately $4,164 higher same-month sales.
A39: Estimated equation | B39: ="Estimated Sales = "&TEXT(Simple_Linear_Reg_Analysis!$B$34,"$#,##0")&" + "&TEXT(Simple_Linear_Reg_Analysis!$B$33,"0.000")&" × Marketing Spend" -> Estimated Sales = $52,628 + 4.164 × Marketing Spend
A40: Prediction or scenario result | B40: Not applicable—the requested objective is association analysis rather than a future sales forecast.
A41: Model reliability | B41: ="The model explains "&TEXT(Simple_Linear_Reg_Analysis!$B$8,"0.0%")&" of observed sales variation; typical in-sample error is approximately "&TEXT(Simple_Linear_Reg_Analysis!$B$10,"$#,##0")&"." -> The model explains 99.7% of observed sales variation; typical in-sample error is approximately $2,644.
A42: Statistical evidence | B42: ="The slope p-value is "&TEXT(Simple_Linear_Reg_Analysis!$E$33,"0.00E+00")&"; the 95% confidence interval per $1,000 is "&TEXT(Simple_Linear_Reg_Analysis!$F$33*1000,"$#,##0")&" to "&TEXT(Simple_Linear_Reg_Analysis!$G$33*1000,"$#,##0")&"." -> The slope p-value is 4.10E-30; the 95% confidence interval per $1,000 is $4,072 to $4,256.
A43: Limitations and diagnostics | B43: ="Residuals remain strongly related to the provided seasonality context (correlation "&TEXT(Simple_Linear_Reg_Analysis!$B$29,"0.00")&"). Because spend and sales also rise over time, the relationship may partly reflect seasonality or trend." -> Residuals remain strongly related to the provided seasonality context (correlation 0.90). Because spend and sales also rise over time, the relationship may partly reflect seasonality or trend.
A44: Business recommendation | B44: Use the estimate for directional budgeting only. Add seasonality or month effects and validate on additional future periods before using the coefficient for high-impact decisions.
A45: Model classification | B45: Use with caution
A46: Causality caution | B46: This is a same-period association. It does not prove that additional marketing spend caused the observed sales increase.

Sheet Simple_Linear_Reg_Analysis
A1: Simple Linear Regression Analysis
A3: Model Overview
A4: Outcome variable | B4: Sales
A5: Model type | B5: Simple linear regression
A6: Predictor list (formula order) | B6: Marketing Spend
A7: Observations | B7: =COUNT(Simple_Linear!B7:B30) -> 24
A8: R-squared | B8: =RSQ(Simple_Linear!C7:C30,Simple_Linear!B7:B30) -> 0.99749536
A9: Adjusted R-squared | B9: =1-(1-B8)*(B7-1)/(B7-2) -> 0.99738151
A10: Typical error (STEYX) | B10: =STEYX(Simple_Linear!C7:C30,Simple_Linear!B7:B30) -> 2644.2525
A11: Pearson correlation | B11: =CORREL(Simple_Linear!B7:B30,Simple_Linear!C7:C30) -> 0.9987469
A12: Validation approach | B12: First 18 months used for training; final 6 months checked as a time holdout.
A13: Holdout MAE | B13: =SUMPRODUCT(ABS(E69:E74))/COUNT(E69:E74) -> 2093.1432
A14: Holdout RMSE | B14: =SQRT(SUMSQ(E69:E74)/COUNT(E69:E74)) -> 2565.3519
A15: Model classification | B15: Use with caution
A18: Top Predictor Summary
A19: Rank | B19: Predictor | C19: Direction | D19: Coefficient | E19: Reliability | F19: Business Interpretation | G19: Notes
A20: 1 | B20: Marketing Spend | C20: Positive | D20: =B33 -> 4.1640835 | E20: Use with caution | F20: ="Each additional $1,000 is associated with approximately "&TEXT(D20*1000,"$#,##0")&" higher same-month sales." -> Each additional $1,000 is associated with approximately $4,164 higher same-month sales. | G20: Strong estimate, but time trend and omitted seasonality may inflate it; association, not causation.
A23: Diagnostics Summary
A24: Check | B24: Status | C24: Business Meaning
A25: Linearity | B25: No material concern | C25: The observed spend-sales pattern is close to a straight line over the available range.
A26: Outliers | B26: No material concern | C26: The largest residual is below twice the typical model error.
A27: Multicollinearity | B27: No material concern | C27: Only one predictor is included, so overlapping predictors are not applicable.
A28: Validation | B28: Use with caution | C28: The six-month time holdout is accurate but small and does not resolve the common upward trend.
A29: Omitted seasonality | B29: =CORREL(D41:D64,E41:E64) -> 0.904787 | C29: Material concern: residuals remain strongly associated with the supplied seasonality context.
A30: Data leakage | B30: No material concern | C30: Marketing spend is a contemporaneous input and is not calculated from sales.
A32: Coefficient | B32: Estimate | C32: Std. Error | D32: t-stat | E32: p-value | F32: 95% CI Low | G32: 95% CI High
A33: Marketing Spend | B33: =SLOPE(Simple_Linear!C7:C30,Simple_Linear!B7:B30) -> 4.1640835 | C33: =STEYX(Simple_Linear!C7:C30,Simple_Linear!B7:B30)/SQRT(DEVSQ(Simple_Linear!B7:B30)) -> 0.044486195 | D33: =B33/C33 -> 93.603947 | E33: =_xlfn.T.DIST.2T(ABS(D33),B7-2) -> 4.0972455e-30 | F33: =B33-_xlfn.T.INV.2T(0.05,B7-2)*C33 -> 4.0718248 | G33: =B33+_xlfn.T.INV.2T(0.05,B7-2)*C33 -> 4.2563422
A34: Intercept | B34: =INTERCEPT(Simple_Linear!C7:C30,Simple_Linear!B7:B30) -> 52627.631
A40: Month | B40: Actual Sales | C40: Predicted Sales | D40: Residual | E40: Seasonality Context
A41: =Simple_Linear!A7 -> 45292 | B41: =Simple_Linear!C7 -> 103000 | C41: =$B$34+$B$33*Simple_Linear!B7 -> 102596.63 | D41: =B41-C41 -> 403.36744 | E41: =Simple_Linear!D7 -> 3000
A42: =Simple_Linear!A8 -> 45323 | B42: =Simple_Linear!C8 -> 111198 | C42: =$B$34+$B$33*Simple_Linear!B8 -> 113631.45 | D42: =B42-C42 -> -2433.4538 | E42: =Simple_Linear!D8 -> -2500
A43: =Simple_Linear!A9 -> 45352 | B43: =Simple_Linear!C9 -> 115150 | C43: =$B$34+$B$33*Simple_Linear!B9 -> 115088.88 | D43: =B43-C43 -> 61.11702 | E43: =Simple_Linear!D9 -> 1500
A44: =Simple_Linear!A10 -> 45383 | B44: =Simple_Linear!C10 -> 131478 | C44: =$B$34+$B$33*Simple_Linear!B10 -> 126956.52 | D44: =B44-C44 -> 4521.4791 | E44: =Simple_Linear!D10 -> 4200
A45: =Simple_Linear!A11 -> 45413 | B45: =Simple_Linear!C11 -> 128750 | C45: =$B$34+$B$33*Simple_Linear!B11 -> 131745.22 | D45: =B45-C45 -> -2995.2169 | E45: =Simple_Linear!D11 -> -1200
A46: =Simple_Linear!A12 -> 45444 | B46: =Simple_Linear!C12 -> 144548 | C46: =$B$34+$B$33*Simple_Linear!B12 -> 142780.04 | D46: =B46-C46 -> 1767.9619 | E46: =Simple_Linear!D12 -> 2000
A47: =Simple_Linear!A13 -> 45474 | B47: =Simple_Linear!C13 -> 144500 | C47: =$B$34+$B$33*Simple_Linear!B13 -> 144237.47 | D47: =B47-C47 -> 262.5327 | E47: =Simple_Linear!D13 -> 3000
A48: =Simple_Linear!A14 -> 45505 | B48: =Simple_Linear!C14 -> 153528 | C48: =$B$34+$B$33*Simple_Linear!B14 -> 156105.11 | D48: =B48-C48 -> -2577.1052 | E48: =Simple_Linear!D14 -> -2500
A49: =Simple_Linear!A15 -> 45536 | B49: =Simple_Linear!C15 -> 160800 | C49: =$B$34+$B$33*Simple_Linear!B15 -> 160893.8 | D49: =B49-C49 -> -93.801189 | E49: =Simple_Linear!D15 -> 1500
A50: =Simple_Linear!A16 -> 45566 | B50: =Simple_Linear!C16 -> 176298 | C50: =$B$34+$B$33*Simple_Linear!B16 -> 171928.62 | D50: =B50-C50 -> 4369.3776 | E50: =Simple_Linear!D16 -> 4200
A51: =Simple_Linear!A17 -> 45597 | B51: =Simple_Linear!C17 -> 170250 | C51: =$B$34+$B$33*Simple_Linear!B17 -> 173386.05 | D51: =B51-C51 -> -3136.0516 | E51: =Simple_Linear!D17 -> -1200
A52: =Simple_Linear!A18 -> 45627 | B52: =Simple_Linear!C18 -> 186878 | C52: =$B$34+$B$33*Simple_Linear!B18 -> 185253.69 | D52: =B52-C52 -> 1624.3105 | E52: =Simple_Linear!D18 -> 2000
... A64: =Simple_Linear!A30 -> 45992 | B64: =Simple_Linear!C30 -> 274028 | C64: =$B$34+$B$33*Simple_Linear!B30 -> 272699.44 | D64: =B64-C64 -> 1328.5575 | E64: =Simple_Linear!D30 -> 2000
A68: Holdout Month | B68: Actual Sales | C68: Predicted Sales | D68: Residual | E68: Absolute Error
A69: =Simple_Linear!A25 -> 45839 | B69: =Simple_Linear!C25 -> 231650 | C69: =INTERCEPT(Simple_Linear!$C$7:$C$24,Simple_Linear!$B$7:$B$24)+SLOPE(Simple_Linear!$C$7:$C$24,Simple_Linear!$B$7:$B$24)*Simple_Linear!B25 -> 231910.7 | D69: =B69-C69 -> -260.69963 | E69: =ABS(D69) -> 260.69963
A70: =Simple_Linear!A26 -> 45870 | B70: =Simple_Linear!C26 -> 240678 | C70: =INTERCEPT(Simple_Linear!$C$7:$C$24,Simple_Linear!$B$7:$B$24)+SLOPE(Simple_Linear!$C$7:$C$24,Simple_Linear!$B$7:$B$24)*Simple_Linear!B26 -> 243806 | D70: =B70-C70 -> -3127.9973 | E70: =ABS(D70) -> 3127.9973
A71: =Simple_Linear!A27 -> 45901 | B71: =Simple_Linear!C27 -> 247950 | C71: =INTERCEPT(Simple_Linear!$C$7:$C$24,Simple_Linear!$B$7:$B$24)+SLOPE(Simple_Linear!$C$7:$C$24,Simple_Linear!$B$7:$B$24)*Simple_Linear!B27 -> 248605.85 | D71: =B71-C71 -> -655.85426 | E71: =ABS(D71) -> 655.85426
A72: =Simple_Linear!A28 -> 45931 | B72: =Simple_Linear!C28 -> 263448 | C72: =INTERCEPT(Simple_Linear!$C$7:$C$24,Simple_Linear!$B$7:$B$24)+SLOPE(Simple_Linear!$C$7:$C$24,Simple_Linear!$B$7:$B$24)*Simple_Linear!B28 -> 259666.39 | D72: =B72-C72 -> 3781.6058 | E72: =ABS(D72) -> 3781.6058
A73: =Simple_Linear!A29 -> 45962 | B73: =Simple_Linear!C29 -> 257400 | C73: =INTERCEPT(Simple_Linear!$C$7:$C$24,Simple_Linear!$B$7:$B$24)+SLOPE(Simple_Linear!$C$7:$C$24,Simple_Linear!$B$7:$B$24)*Simple_Linear!B29 -> 261127.22 | D73: =B73-C73 -> -3727.2202 | E73: =ABS(D73) -> 3727.2202
A74: =Simple_Linear!A30 -> 45992 | B74: =Simple_Linear!C30 -> 274028 | C74: =INTERCEPT(Simple_Linear!$C$7:$C$24,Simple_Linear!$B$7:$B$24)+SLOPE(Simple_Linear!$C$7:$C$24,Simple_Linear!$B$7:$B$24)*Simple_Linear!B30 -> 273022.52 | D74: =B74-C74 -> 1005.4821 | E74: =ABS(D74) -> 1005.4821

Sheet Multiple_Regression
A1: Multiple Regression: Monthly Sales Drivers
A2: Unsolved test case. Run the regression skill against this sheet and retain both mandatory Excel outputs.
A3: Business question | B3: Which controllable and operating factors are most useful for estimating monthly sales?
A4: Design note | B4: Continuous outcome with four candidate predictors. Coefficients must be interpreted conditionally, and the technical summary should report only the three most relevant predictors.
A6: Month | B6: Marketing Spend | C6: Average Discount | D6: Seasonality Index | E6: Active Sales Reps | F6: Sales | H6: Predicted Sales | I6: Residual
A7: 44927 | B7: 18000 | C7: 0.04 | D7: 0.91 | E7: 8 | F7: 148490 | H7: =Regression_Model_Summary!$B$35+Regression_Model_Summary!$B$31*B7+Regression_Model_Summary!$B$32*C7+Regression_Model_Summary!$B$33*D7+Regression_Model_Summary!$B$34*E7 -> 150549.45 | I7: =F7-H7 -> -2059.4509
A8: 44958 | B8: 21400 | C8: 0.048 | D8: 0.95 | E8: 9 | F8: 169400 | H8: =Regression_Model_Summary!$B$35+Regression_Model_Summary!$B$31*B8+Regression_Model_Summary!$B$32*C8+Regression_Model_Summary!$B$33*D8+Regression_Model_Summary!$B$34*E8 -> 166718.52 | I8: =F8-H8 -> 2681.482
A9: 44986 | B9: 24800 | C9: 0.056 | D9: 1.02 | E9: 10 | F9: 182780 | H9: =Regression_Model_Summary!$B$35+Regression_Model_Summary!$B$31*B9+Regression_Model_Summary!$B$32*C9+Regression_Model_Summary!$B$33*D9+Regression_Model_Summary!$B$34*E9 -> 183986.03 | I9: =F9-H9 -> -1206.0313
A10: 45017 | B10: 28200 | C10: 0.064 | D10: 1.08 | E10: 11 | F10: 202570 | H10: =Regression_Model_Summary!$B$35+Regression_Model_Summary!$B$31*B10+Regression_Model_Summary!$B$32*C10+Regression_Model_Summary!$B$33*D10+Regression_Model_Summary!$B$34*E10 -> 200887.4 | I10: =F10-H10 -> 1682.6041
A11: 45047 | B11: 31600 | C11: 0.072 | D11: 1.13 | E11: 12 | F11: 214970 | H11: =Regression_Model_Summary!$B$35+Regression_Model_Summary!$B$31*B11+Regression_Model_Summary!$B$32*C11+Regression_Model_Summary!$B$33*D11+Regression_Model_Summary!$B$34*E11 -> 217422.61 | I11: =F11-H11 -> -2452.6117
A12: 45078 | B12: 35000 | C12: 0.08 | D12: 1.17 | E12: 8 | F12: 206780 | H12: =Regression_Model_Summary!$B$35+Regression_Model_Summary!$B$31*B12+Regression_Model_Summary!$B$32*C12+Regression_Model_Summary!$B$33*D12+Regression_Model_Summary!$B$34*E12 -> 209255.99 | I12: =F12-H12 -> -2475.9934
A13: 45108 | B13: 38400 | C13: 0.04 | D13: 1.12 | E13: 9 | F13: 232520 | H13: =Regression_Model_Summary!$B$35+Regression_Model_Summary!$B$31*B13+Regression_Model_Summary!$B$32*C13+Regression_Model_Summary!$B$33*D13+Regression_Model_Summary!$B$34*E13 -> 230783.06 | I13: =F13-H13 -> 1736.9353
A14: 45139 | B14: 41800 | C14: 0.048 | D14: 1.05 | E14: 10 | F14: 241840 | H14: =Regression_Model_Summary!$B$35+Regression_Model_Summary!$B$31*B14+Regression_Model_Summary!$B$32*C14+Regression_Model_Summary!$B$33*D14+Regression_Model_Summary!$B$34*E14 -> 242924.5 | I14: =F14-H14 -> -1084.4954
A15: 45170 | B15: 45200 | C15: 0.056 | D15: 0.98 | E15: 11 | F15: 257860 | H15: =Regression_Model_Summary!$B$35+Regression_Model_Summary!$B$31*B15+Regression_Model_Summary!$B$32*C15+Regression_Model_Summary!$B$33*D15+Regression_Model_Summary!$B$34*E15 -> 255065.93 | I15: =F15-H15 -> 2794.0738
A16: 45200 | B16: 48600 | C16: 0.064 | D16: 0.94 | E16: 12 | F16: 267650 | H16: =Regression_Model_Summary!$B$35+Regression_Model_Summary!$B$31*B16+Regression_Model_Summary!$B$32*C16+Regression_Model_Summary!$B$33*D16+Regression_Model_Summary!$B$34*E16 -> 268305.8 | I16: =F16-H16 -> -655.80317
A17: 45231 | B17: 19100 | C17: 0.072 | D17: 0.97 | E17: 8 | F17: 148955 | H17: =Regression_Model_Summary!$B$35+Regression_Model_Summary!$B$31*B17+Regression_Model_Summary!$B$32*C17+Regression_Model_Summary!$B$33*D17+Regression_Model_Summary!$B$34*E17 -> 150626.72 | I17: =F17-H17 -> -1671.7171
A18: 45261 | B18: 22500 | C18: 0.08 | D18: 1.1 | E18: 9 | F18: 172475 | H18: =Regression_Model_Summary!$B$35+Regression_Model_Summary!$B$31*B18+Regression_Model_Summary!$B$32*C18+Regression_Model_Summary!$B$33*D18+Regression_Model_Summary!$B$34*E18 -> 170091.12 | I18: =F18-H18 -> 2383.877
... A36: 45809 | B36: 50800 | C36: 0.08 | D36: 1.17 | E36: 12 | F36: 279210 | H36: =Regression_Model_Summary!$B$35+Regression_Model_Summary!$B$31*B36+Regression_Model_Summary!$B$32*C36+Regression_Model_Summary!$B$33*D36+Regression_Model_Summary!$B$34*E36 -> 281141.31 | I36: =F36-H36 -> -1931.3149
A39: Regression Analysis Results
A41: Business question | B41: Estimate monthly sales using marketing spend, average discount, seasonality index, and active sales representatives.
A42: Model used | B42: Multiple linear regression with Sales as the continuous outcome and four numeric predictors. Coefficients are conditional associations holding the other included factors constant.
A43: Data scope | B43: 30 monthly observations from Jan-2023 through Jun-2025; no missing or excluded rows.
A44: Key driver 1 | B44: ="Marketing: each additional $1,000 of spend is associated with approximately "&TEXT(Regression_Model_Summary!$B$31*1000,"$#,##0")&" higher monthly sales." -> Marketing: each additional $1,000 of spend is associated with approximately $3,318 higher monthly sales.
A45: Key driver 2 | B45: ="Sales capacity: each additional active representative is associated with approximately "&TEXT(Regression_Model_Summary!$B$34,"$#,##0")&" higher monthly sales." -> Sales capacity: each additional active representative is associated with approximately $4,867 higher monthly sales.
A46: Key driver 3 | B46: ="Seasonality: a 0.10 increase in the seasonality index is associated with approximately "&TEXT(Regression_Model_Summary!$B$33*0.1,"$#,##0")&" higher monthly sales." -> Seasonality: a 0.10 increase in the seasonality index is associated with approximately $3,661 higher monthly sales.
A47: Estimated equation | B47: ="Sales = "&TEXT(Regression_Model_Summary!$B$35,"$#,##0")&" + "&TEXT(Regression_Model_Summary!$B$31,"0.000")&"×Marketing Spend "&IF(Regression_Model_Summary!$B$32<0,"- ","+ ")&TEXT(ABS(Regression_Model_Summary!$B$32),"$#,##0")&"×Average Discount + "&TEXT(Regression_Model_Summary!$B$33,"$#,##0")&"×Seasonality Index + "&TEXT(Regression_Model_Summary!$B$34,"$#,##0")&"×Active Reps" -> Sales = $25,789 + 3.318×Marketing Spend - $180,278×Average Discount + $36,615×Seasonality Index + $4,867×Active Reps
A48: Prediction result | B48: ="Fitted monthly estimates are shown in H7:H36. For planning, use an approximate range of predicted sales ±"&TEXT(2*Regression_Model_Summary!$B$10,"$#,##0")&"." -> Fitted monthly estimates are shown in H7:H36. For planning, use an approximate range of predicted sales ±$4,339.
A49: Model reliability | B49: ="Adjusted R² is "&TEXT(Regression_Model_Summary!$B$9,"0.0%")&"; typical in-sample error is "&TEXT(Regression_Model_Summary!$B$10,"$#,##0")&". Six-month holdout RMSE is "&TEXT(Regression_Model_Summary!$B$13,"$#,##0")&"." -> Adjusted R² is 99.7%; typical in-sample error is $2,170. Six-month holdout RMSE is $2,015.
A50: Limitations and diagnostics | B50: No material outlier or multicollinearity concern. The holdout covers only six months, and future estimates should use planned—not after-the-fact—discount and staffing inputs.
A51: Business recommendation | B51: Use the model for monthly budgeting and scenario planning within the observed input ranges. Refresh it as new months arrive and investigate material residuals.
A52: Model classification | B52: Ready for decision support
A53: Causality caution | B53: The coefficients describe associations after controlling for the other included predictors; they do not prove causal impact.

Sheet Regression_Model_Summary
A1: Regression Model Summary
A3: Model overview
A4: Outcome variable | B4: Sales
A5: Model type | B5: Multiple linear regression
A6: Predictor list (formula order) | B6: Marketing Spend; Average Discount; Seasonality Index; Active Sales Reps
A7: Observations | B7: =COUNT(Multiple_Regression!F7:F36) -> 30
A8: R-squared | B8: =INDEX(LINEST(Multiple_Regression!F7:F36,Multiple_Regression!B7:E36,TRUE,TRUE),3,1) -> 0.99724699
A9: Adjusted R-squared | B9: =1-(1-B8)*(B7-1)/(B7-4-1) -> 0.99680651
A10: Typical error | B10: =INDEX(LINEST(Multiple_Regression!F7:F36,Multiple_Regression!B7:E36,TRUE,TRUE),3,2) -> 2169.7053
A11: Validation approach | B11: First 24 months used for training; final 6 months used as a time holdout.
A12: Holdout MAE | B12: =SUMPRODUCT(ABS(E61:E66))/COUNT(E61:E66) -> 1877.0202
A13: Holdout RMSE | B13: =SQRT(SUMSQ(E61:E66)/COUNT(E61:E66)) -> 2015.1255
A14: Model classification | B14: Ready for decision support
A17: Top predictor summary
A18: Rank | B18: Predictor | C18: Direction | D18: Coefficient | E18: Reliability | F18: Business Interpretation | G18: Notes
A19: 1 | B19: Marketing Spend | C19: Positive | D19: =B31 -> 3.3175173 | E19: Verified estimate | F19: ="Each additional $1,000 is associated with approximately "&TEXT(D19*1000,"$#,##0")&" higher sales, holding other factors constant." -> Each additional $1,000 is associated with approximately $3,318 higher sales, holding other factors constant. | G19: Association, not causation
A20: 2 | B20: Active Sales Reps | C20: Positive | D20: =B34 -> 4867.1371 | E20: Verified estimate | F20: ="Each additional active representative is associated with approximately "&TEXT(D20,"$#,##0")&" higher monthly sales." -> Each additional active representative is associated with approximately $4,867 higher monthly sales. | G20: Use planned staffing levels for forecasts
A21: 3 | B21: Seasonality Index | C21: Positive | D21: =B33 -> 36614.876 | E21: Verified estimate | F21: ="A 0.10 increase in the index is associated with approximately "&TEXT(D21*0.1,"$#,##0")&" higher sales." -> A 0.10 increase in the index is associated with approximately $3,661 higher sales. | G21: Requires a credible future seasonality assumption
A24: Diagnostics summary
A25: Check | B25: Status | C25: Business Meaning
A26: Linearity | B26: No material concern | C26: Residual size is small and does not indicate a material misspecification within the observed range.
A27: Outliers | B27: No material concern | C27: Largest residual is about $3,234 and maximum Cook's distance is about 0.10.
A28: Multicollinearity | B28: No material concern | C28: All predictor VIF values are below 2.2, supporting stable conditional interpretation.
A29: Validation | B29: No material concern | C29: Six-month time holdout error is comparable to the in-sample typical error.
A30: Data leakage | B30: No material concern | C30: Inputs are appropriate if planned values are available before the month closes.
A31: Marketing Spend | B31: =INDEX(LINEST(Multiple_Regression!F7:F36,Multiple_Regression!B7:E36,TRUE,TRUE),1,4) -> 3.3175173 | C31: =INDEX(LINEST(Multiple_Regression!F7:F36,Multiple_Regression!B7:E36,TRUE,TRUE),2,4) -> 0.05489053 | D31: =B31/C31 -> 60.438791 | E31: =_xlfn.T.DIST.2T(ABS(D31),B7-5) -> 1.2715341e-28 | F31: =B31-_xlfn.T.INV.2T(0.05,B7-5)*C31 -> 3.2044681 | G31: =B31+_xlfn.T.INV.2T(0.05,B7-5)*C31 -> 3.4305665
A32: Average Discount | B32: =INDEX(LINEST(Multiple_Regression!F7:F36,Multiple_Regression!B7:E36,TRUE,TRUE),1,3) -> -180277.98 | C32: =INDEX(LINEST(Multiple_Regression!F7:F36,Multiple_Regression!B7:E36,TRUE,TRUE),2,3) -> 36900.777 | D32: =B32/C32 -> -4.8854792 | E32: =_xlfn.T.DIST.2T(ABS(D32),B7-5) -> 5.0134283e-05 | F32: =B32-_xlfn.T.INV.2T(0.05,B7-5)*C32 -> -256276.55 | G32: =B32+_xlfn.T.INV.2T(0.05,B7-5)*C32 -> -104279.41
A33: Seasonality Index | B33: =INDEX(LINEST(Multiple_Regression!F7:F36,Multiple_Regression!B7:E36,TRUE,TRUE),1,2) -> 36614.876 | C33: =INDEX(LINEST(Multiple_Regression!F7:F36,Multiple_Regression!B7:E36,TRUE,TRUE),2,2) -> 6841.8646 | D33: =B33/C33 -> 5.3515931 | E33: =_xlfn.T.DIST.2T(ABS(D33),B7-5) -> 1.5047118e-05 | F33: =B33-_xlfn.T.INV.2T(0.05,B7-5)*C33 -> 22523.792 | G33: =B33+_xlfn.T.INV.2T(0.05,B7-5)*C33 -> 50705.959
A34: Active Sales Reps | B34: =INDEX(LINEST(Multiple_Regression!F7:F36,Multiple_Regression!B7:E36,TRUE,TRUE),1,1) -> 4867.1371 | C34: =INDEX(LINEST(Multiple_Regression!F7:F36,Multiple_Regression!B7:E36,TRUE,TRUE),2,1) -> 325.69799 | D34: =B34/C34 -> 14.943712 | E34: =_xlfn.T.DIST.2T(ABS(D34),B7-5) -> 5.7096613e-14 | F34: =B34-_xlfn.T.INV.2T(0.05,B7-5)*C34 -> 4196.3495 | G34: =B34+_xlfn.T.INV.2T(0.05,B7-5)*C34 -> 5537.9246
A35: Intercept | B35: =INDEX(LINEST(Multiple_Regression!F7:F36,Multiple_Regression!B7:E36,TRUE,TRUE),1,5) -> 25788.626 | C35: =INDEX(LINEST(Multiple_Regression!F7:F36,Multiple_Regression!B7:E36,TRUE,TRUE),2,5) -> 6204.4074 | D35: =B35/C35 -> 4.156501 | E35: =_xlfn.T.DIST.2T(ABS(D35),B7-5) -> 0.00033116591 | F35: =B35-_xlfn.T.INV.2T(0.05,B7-5)*C35 -> 13010.409 | G35: =B35+_xlfn.T.INV.2T(0.05,B7-5)*C35 -> 38566.842
A39: VIF diagnostics
A40: Predictor | B40: VIF
A41: Marketing Spend | B41: 1.8466489
A42: Average Discount | B42: 1.6197857
A43: Seasonality Index | B43: 2.1166795
A44: Active Sales Reps | B44: 1.35201
A47: Holdout validation
A48: Training period | B48: Jan-2023 to Dec-2024
A49: Holdout period | B49: Jan-2025 to Jun-2025
A50: Holdout coefficients use LINEST on training rows only.
A60: Month | B60: Actual Sales | C60: Predicted Sales | D60: Residual | E60: Absolute Error
A61: =Multiple_Regression!A31 -> 45658 | B61: =Multiple_Regression!F31 -> 220920 | C61: =INDEX(LINEST(Multiple_Regression!$F$7:$F$30,Multiple_Regression!$B$7:$E$30,TRUE,TRUE),1,5)+INDEX(LINEST(Multiple_Regression!$F$7:$F$30,Multiple_Regression!$B$7:$E$30,TRUE,TRUE),1,4)*Multiple_Regression!B31+INDEX(LINEST(Multiple_Regression!$F$7:$F$30,Multiple_Regression!$B$7:$E$30,TRUE,TRUE),1,3)*Multiple_Regression!C31+INDEX(LINEST(Multiple_Regression!$F$7:$F$30,Multiple_Regression!$B$7:$E$30,TRUE,TRUE),1,2)*Multiple_Regression!D31+INDEX(LINEST(Multiple_Regression!$F$7:$F$30,Multiple_Regression!$B$7:$E$30,TRUE,TRUE),1,1)*Multiple_Regression!E31 -> 222852.59 | D61: =B61-C61 -> -1932.5937 | E61: =ABS(D61) -> 1932.5937
A62: =Multiple_Regression!A32 -> 45689 | B62: =Multiple_Regression!F32 -> 212730 | C62: =INDEX(LINEST(Multiple_Regression!$F$7:$F$30,Multiple_Regression!$B$7:$E$30,TRUE,TRUE),1,5)+INDEX(LINEST(Multiple_Regression!$F$7:$F$30,Multiple_Regression!$B$7:$E$30,TRUE,TRUE),1,4)*Multiple_Regression!B32+INDEX(LINEST(Multiple_Regression!$F$7:$F$30,Multiple_Regression!$B$7:$E$30,TRUE,TRUE),1,3)*Multiple_Regression!C32+INDEX(LINEST(Multiple_Regression!$F$7:$F$30,Multiple_Regression!$B$7:$E$30,TRUE,TRUE),1,2)*Multiple_Regression!D32+INDEX(LINEST(Multiple_Regression!$F$7:$F$30,Multiple_Regression!$B$7:$E$30,TRUE,TRUE),1,1)*Multiple_Regression!E32 -> 214073.72 | D62: =B62-C62 -> -1343.721 | E62: =ABS(D62) -> 1343.721
A63: =Multiple_Regression!A33 -> 45717 | B63: =Multiple_Regression!F33 -> 234510 | C63: =INDEX(LINEST(Multiple_Regression!$F$7:$F$30,Multiple_Regression!$B$7:$E$30,TRUE,TRUE),1,5)+INDEX(LINEST(Multiple_Regression!$F$7:$F$30,Multiple_Regression!$B$7:$E$30,TRUE,TRUE),1,4)*Multiple_Regression!B33+INDEX(LINEST(Multiple_Regression!$F$7:$F$30,Multiple_Regression!$B$7:$E$30,TRUE,TRUE),1,3)*Multiple_Regression!C33+INDEX(LINEST(Multiple_Regression!$F$7:$F$30,Multiple_Regression!$B$7:$E$30,TRUE,TRUE),1,2)*Multiple_Regression!D33+INDEX(LINEST(Multiple_Regression!$F$7:$F$30,Multiple_Regression!$B$7:$E$30,TRUE,TRUE),1,1)*Multiple_Regression!E33 -> 231386.65 | D63: =B63-C63 -> 3123.3479 | E63: =ABS(D63) -> 3123.3479
A64: =Multiple_Regression!A34 -> 45748 | B64: =Multiple_Regression!F34 -> 247600 | C64: =INDEX(LINEST(Multiple_Regression!$F$7:$F$30,Multiple_Regression!$B$7:$E$30,TRUE,TRUE),1,5)+INDEX(LINEST(Multiple_Regression!$F$7:$F$30,Multiple_Regression!$B$7:$E$30,TRUE,TRUE),1,4)*Multiple_Regression!B34+INDEX(LINEST(Multiple_Regression!$F$7:$F$30,Multiple_Regression!$B$7:$E$30,TRUE,TRUE),1,3)*Multiple_Regression!C34+INDEX(LINEST(Multiple_Regression!$F$7:$F$30,Multiple_Regression!$B$7:$E$30,TRUE,TRUE),1,2)*Multiple_Regression!D34+INDEX(LINEST(Multiple_Regression!$F$7:$F$30,Multiple_Regression!$B$7:$E$30,TRUE,TRUE),1,1)*Multiple_Regression!E34 -> 248339.57 | D64: =B64-C64 -> -739.5693 | E64: =ABS(D64) -> 739.5693
A65: =Multiple_Regression!A35 -> 45778 | B65: =Multiple_Regression!F35 -> 267100 | C65: =INDEX(LINEST(Multiple_Regression!$F$7:$F$30,Multiple_Regression!$B$7:$E$30,TRUE,TRUE),1,5)+INDEX(LINEST(Multiple_Regression!$F$7:$F$30,Multiple_Regression!$B$7:$E$30,TRUE,TRUE),1,4)*Multiple_Regression!B35+INDEX(LINEST(Multiple_Regression!$F$7:$F$30,Multiple_Regression!$B$7:$E$30,TRUE,TRUE),1,3)*Multiple_Regression!C35+INDEX(LINEST(Multiple_Regression!$F$7:$F$30,Multiple_Regression!$B$7:$E$30,TRUE,TRUE),1,2)*Multiple_Regression!D35+INDEX(LINEST(Multiple_Regression!$F$7:$F$30,Multiple_Regression!$B$7:$E$30,TRUE,TRUE),1,1)*Multiple_Regression!E35 -> 264932.47 | D65: =B65-C65 -> 2167.5274 | E65: =ABS(D65) -> 2167.5274
A66: =Multiple_Regression!A36 -> 45809 | B66: =Multiple_Regression!F36 -> 279210 | C66: =INDEX(LINEST(Multiple_Regression!$F$7:$F$30,Multiple_Regression!$B$7:$E$30,TRUE,TRUE),1,5)+INDEX(LINEST(Multiple_Regression!$F$7:$F$30,Multiple_Regression!$B$7:$E$30,TRUE,TRUE),1,4)*Multiple_Regression!B36+INDEX(LINEST(Multiple_Regression!$F$7:$F$30,Multiple_Regression!$B$7:$E$30,TRUE,TRUE),1,3)*Multiple_Regression!C36+INDEX(LINEST(Multiple_Regression!$F$7:$F$30,Multiple_Regression!$B$7:$E$30,TRUE,TRUE),1,2)*Multiple_Regression!D36+INDEX(LINEST(Multiple_Regression!$F$7:$F$30,Multiple_Regression!$B$7:$E$30,TRUE,TRUE),1,1)*Multiple_Regression!E36 -> 281165.36 | D66: =B66-C66 -> -1955.362 | E66: =ABS(D66) -> 1955.362

Sheet Outlier_Influence
A1: Regression Diagnostic: Influential Enterprise Campaign
A2: Unsolved test case. Run the regression skill against this sheet and retain both mandatory Excel outputs.
A3: Business question | B3: Is the marketing-spend relationship stable enough to use across both standard and enterprise campaigns?
A4: Design note | B4: One high-leverage enterprise observation is intentionally included. Compare the fitted relationship with and without it before classifying the model.
A6: Campaign | B6: Campaign Type | C6: Marketing Spend | D6: Revenue | F6: Pooled Prediction | G6: Standard-Model Prediction
A7: Campaign 01 | B7: Standard | C7: 9000 | D7: 77700 | F7: =Outlier_Influence_Reg_Analysis!$C$33+Outlier_Influence_Reg_Analysis!$B$33*C7 -> 15404.373 | G7: =Outlier_Influence_Reg_Analysis!$B$37+Outlier_Influence_Reg_Analysis!$B$36*C7 -> 79555.556
A8: Campaign 02 | B8: Standard | C8: 11600 | D8: 91280 | F8: =Outlier_Influence_Reg_Analysis!$C$33+Outlier_Influence_Reg_Analysis!$B$33*C8 -> 44986.188 | G8: =Outlier_Influence_Reg_Analysis!$B$37+Outlier_Influence_Reg_Analysis!$B$36*C8 -> 89544.698
A9: Campaign 03 | B9: Standard | C9: 14200 | D9: 99060 | F9: =Outlier_Influence_Reg_Analysis!$C$33+Outlier_Influence_Reg_Analysis!$B$33*C9 -> 74568.003 | G9: =Outlier_Influence_Reg_Analysis!$B$37+Outlier_Influence_Reg_Analysis!$B$36*C9 -> 99533.84
A10: Campaign 04 | B10: Standard | C10: 16800 | D10: 111640 | F10: =Outlier_Influence_Reg_Analysis!$C$33+Outlier_Influence_Reg_Analysis!$B$33*C10 -> 104149.82 | G10: =Outlier_Influence_Reg_Analysis!$B$37+Outlier_Influence_Reg_Analysis!$B$36*C10 -> 109522.98
A11: Campaign 05 | B11: Standard | C11: 19400 | D11: 118420 | F11: =Outlier_Influence_Reg_Analysis!$C$33+Outlier_Influence_Reg_Analysis!$B$33*C11 -> 133731.63 | G11: =Outlier_Influence_Reg_Analysis!$B$37+Outlier_Influence_Reg_Analysis!$B$36*C11 -> 119512.12
A12: Campaign 06 | B12: Standard | C12: 22000 | D12: 130200 | F12: =Outlier_Influence_Reg_Analysis!$C$33+Outlier_Influence_Reg_Analysis!$B$33*C12 -> 163313.45 | G12: =Outlier_Influence_Reg_Analysis!$B$37+Outlier_Influence_Reg_Analysis!$B$36*C12 -> 129501.27
A13: Campaign 07 | B13: Standard | C13: 24600 | D13: 136980 | F13: =Outlier_Influence_Reg_Analysis!$C$33+Outlier_Influence_Reg_Analysis!$B$33*C13 -> 192895.26 | G13: =Outlier_Influence_Reg_Analysis!$B$37+Outlier_Influence_Reg_Analysis!$B$36*C13 -> 139490.41
A14: Campaign 08 | B14: Standard | C14: 27200 | D14: 150560 | F14: =Outlier_Influence_Reg_Analysis!$C$33+Outlier_Influence_Reg_Analysis!$B$33*C14 -> 222477.08 | G14: =Outlier_Influence_Reg_Analysis!$B$37+Outlier_Influence_Reg_Analysis!$B$36*C14 -> 149479.55
A15: Campaign 09 | B15: Standard | C15: 9000 | D15: 79300 | F15: =Outlier_Influence_Reg_Analysis!$C$33+Outlier_Influence_Reg_Analysis!$B$33*C15 -> 15404.373 | G15: =Outlier_Influence_Reg_Analysis!$B$37+Outlier_Influence_Reg_Analysis!$B$36*C15 -> 79555.556
A16: Campaign 10 | B16: Standard | C16: 11600 | D16: 91880 | F16: =Outlier_Influence_Reg_Analysis!$C$33+Outlier_Influence_Reg_Analysis!$B$33*C16 -> 44986.188 | G16: =Outlier_Influence_Reg_Analysis!$B$37+Outlier_Influence_Reg_Analysis!$B$36*C16 -> 89544.698
A17: Campaign 11 | B17: Standard | C17: 14200 | D17: 98660 | F17: =Outlier_Influence_Reg_Analysis!$C$33+Outlier_Influence_Reg_Analysis!$B$33*C17 -> 74568.003 | G17: =Outlier_Influence_Reg_Analysis!$B$37+Outlier_Influence_Reg_Analysis!$B$36*C17 -> 99533.84
A18: Campaign 12 | B18: Standard | C18: 16800 | D18: 110440 | F18: =Outlier_Influence_Reg_Analysis!$C$33+Outlier_Influence_Reg_Analysis!$B$33*C18 -> 104149.82 | G18: =Outlier_Influence_Reg_Analysis!$B$37+Outlier_Influence_Reg_Analysis!$B$36*C18 -> 109522.98
... A30: Campaign 24 | B30: Standard | C30: 27200 | D30: 149960 | F30: =Outlier_Influence_Reg_Analysis!$C$33+Outlier_Influence_Reg_Analysis!$B$33*C30 -> 222477.08 | G30: =Outlier_Influence_Reg_Analysis!$B$37+Outlier_Influence_Reg_Analysis!$B$36*C30 -> 149479.55
A33: Regression Analysis Results
A35: Business question | B35: Does marketing spend predict revenue reliably across both standard and enterprise campaigns?
A36: Model used | B36: Simple linear regression of Revenue on Marketing Spend, compared for all campaigns versus standard campaigns only. This directly tests whether the relationship is stable when the enterprise observation is included.
A37: Data scope | B37: 24 campaigns: 23 standard campaigns and one enterprise campaign. No missing rows were excluded.
A38: Key driver | B38: ="For standard campaigns, each additional $1,000 of marketing spend is associated with approximately "&TEXT(Outlier_Influence_Reg_Analysis!$B$36*1000,"$#,##0")&" higher revenue." -> For standard campaigns, each additional $1,000 of marketing spend is associated with approximately $3,842 higher revenue.
A39: Prediction or scenario result | B39: ="The pooled model's typical error is "&TEXT(Outlier_Influence_Reg_Analysis!$B$10,"$#,##0")&", compared with "&TEXT(Outlier_Influence_Reg_Analysis!$B$14,"$#,##0")&" for the standard-only model. Predictions from both equations are shown in F:G." -> The pooled model's typical error is $49,072, compared with $1,524 for the standard-only model. Predictions from both equations are shown in F:G.
A40: Model reliability | B40: ="The enterprise observation changes the slope by "&TEXT(Outlier_Influence_Reg_Analysis!$B$20,"0%")&" and increases standard-campaign MAE from "&TEXT(Outlier_Influence_Reg_Analysis!$B$22,"$#,##0")&" to "&TEXT(Outlier_Influence_Reg_Analysis!$B$21,"$#,##0")&" when one pooled equation is used." -> The enterprise observation changes the slope by 196% and increases standard-campaign MAE from $1,304 to $39,729 when one pooled equation is used.
A41: Limitations and diagnostics | B41: ="Campaign 22 has leverage of "&TEXT(Outlier_Influence_Reg_Analysis!$B$18,"0.00")&" and Cook's distance of "&TEXT(Outlier_Influence_Reg_Analysis!$B$19,"0.0")&", indicating that it dominates the pooled regression. There is only one enterprise observation, so enterprise prediction reliability cannot be validated." -> Campaign 22 has leverage of 0.90 and Cook's distance of 100.2, indicating that it dominates the pooled regression. There is only one enterprise observation, so enterprise prediction reliability cannot be validated.
A42: Business recommendation | B42: Do not use one pooled spend-revenue equation across both campaign types. Use the standard-only model for standard campaigns within the observed spend range, and collect more enterprise campaigns before building a separate enterprise model.
A43: Model classification | B43: Do not rely on this model yet
A44: Causality caution | B44: The slopes describe associations, not proof that additional marketing spend caused the revenue differences.

Sheet Outlier_Influence_Reg_Analysis
A1: Outlier Influence Regression Analysis
A3: Model Overview
A4: Outcome variable | B4: Revenue
A5: Model type | B5: Simple linear regression with influence comparison
A6: Predictor list (formula order) | B6: Marketing Spend
A7: Pooled observations | B7: =COUNT(Outlier_Influence!C7:C30) -> 24
A8: Pooled R-squared | B8: =RSQ(Outlier_Influence!D7:D30,Outlier_Influence!C7:C30) -> 0.95191232
A9: Pooled adjusted R-squared | B9: =1-(1-B8)*(B7-1)/(B7-2) -> 0.94972651
A10: Pooled typical error | B10: =STEYX(Outlier_Influence!D7:D30,Outlier_Influence!C7:C30) -> 49071.696
A11: Standard observations | B11: 23
A12: Standard-only R-squared | B12: 0.99606239
A13: Standard adjusted R-squared | B13: =1-(1-B12)*(B11-1)/(B11-2) -> 0.99587489
A14: Standard typical error | B14: 1524.0259
A15: Validation approach | B15: Influence analysis compares pooled and standard-only fits; enterprise validation is unavailable because only one enterprise campaign exists.
A16: Model classification | B16: Do not rely on this model yet
A18: Enterprise leverage | B18: 0.90111736
A19: Enterprise Cook's distance | B19: 100.15069
A20: Slope change from inclusion | B20: 1.961397
A21: Standard MAE using pooled model | B21: 39729.291
A22: Standard MAE using standard model | B22: 1303.9809
A25: Top Predictor Summary
A26: Rank | B26: Predictor | C26: Direction | D26: Coefficient | E26: Reliability | F26: Business Interpretation | G26: Notes
A27: 1 | B27: Marketing Spend — standard campaigns | C27: Positive | D27: 3.8419777 | E27: Reliable within standard range | F27: ="Each additional $1,000 is associated with approximately "&TEXT(D27*1000,"$#,##0")&" higher revenue for standard campaigns." -> Each additional $1,000 is associated with approximately $3,842 higher revenue for standard campaigns. | G27: Do not extrapolate to enterprise spend levels.
A28: 2 | B28: Marketing Spend — pooled campaigns | C28: Positive | D28: =B33 -> 11.377621 | E28: Unreliable | F28: ="The pooled coefficient implies "&TEXT(D28*1000,"$#,##0")&" per additional $1,000, but it is dominated by one enterprise campaign." -> The pooled coefficient implies $11,378 per additional $1,000, but it is dominated by one enterprise campaign. | G28: Slope changes approximately 196% when the enterprise row is included.
A31: Coefficient Detail
A32: Model | B32: Slope | C32: Intercept | D32: R-squared | E32: Typical Error
A33: Pooled model | B33: =SLOPE(Outlier_Influence!D7:D30,Outlier_Influence!C7:C30) -> 11.377621 | C33: =INTERCEPT(Outlier_Influence!D7:D30,Outlier_Influence!C7:C30) -> -86994.219 | D33: =RSQ(Outlier_Influence!D7:D30,Outlier_Influence!C7:C30) -> 0.95191232 | E33: =STEYX(Outlier_Influence!D7:D30,Outlier_Influence!C7:C30) -> 49071.696
A36: Standard-only slope | B36: 3.8419777
A37: Standard-only intercept | B37: 44977.756
A39: Diagnostics Summary
A40: Check | B40: Status | C40: Business Meaning
A41: Linearity | B41: Material concern | C41: One straight line does not represent both campaign regimes reliably.
A42: Outliers | B42: Material concern | C42: Campaign 22 has extreme leverage and Cook's distance, materially changing the fitted relationship.
A43: Multicollinearity | B43: No material concern | C43: Only one predictor is included.
A44: Validation | B44: Material concern | C44: Only one enterprise campaign exists, so enterprise prediction accuracy cannot be tested.
A45: Data leakage | B45: No material concern | C45: Marketing spend is available before campaign revenue is observed.
A48: Enterprise Campaign Check
A49: Campaign | B49: Spend | C49: Actual Revenue | D49: Standard-Model Revenue | E49: Difference
A50: =Outlier_Influence!A28 -> Campaign 22 | B50: =Outlier_Influence!C28 -> 105000 | C50: =Outlier_Influence!D28 -> 1180000 | D50: =$B$37+$B$36*B50 -> 448385.42 | E50: =C50-D50 -> 731614.58

Sheet Multicollinearity
A1: Regression Diagnostic: Overlapping Marketing Predictors
A2: Unsolved test case. Run the regression skill against this sheet and retain both mandatory Excel outputs.
A3: Business question | B3: Can paid media spend, campaign reach, and brand impressions be interpreted as separate sales drivers?
A4: Design note | B4: The three predictors are intentionally near-duplicates. Strong overall fit must not be confused with reliable individual coefficient estimates.
A6: Region | B6: Paid Media Spend | C6: Campaign Reach (000s) | D6: Brand Impressions (000s) | E6: Sales | G6: Predicted Sales | H6: Residual
A7: Region 01 | B7: 16000 | C7: 255 | D7: 501 | E7: 112000 | G7: =Multicollinearity_Reg_Analysis!$B$37+Multicollinearity_Reg_Analysis!$B$34*B7+Multicollinearity_Reg_Analysis!$B$35*C7+Multicollinearity_Reg_Analysis!$B$36*D7 -> 112250.18 | H7: =E7-G7 -> -250.17504
A8: Region 02 | B8: 17450 | C8: 283 | D8: 550 | E8: 119342 | G8: =Multicollinearity_Reg_Analysis!$B$37+Multicollinearity_Reg_Analysis!$B$34*B8+Multicollinearity_Reg_Analysis!$B$35*C8+Multicollinearity_Reg_Analysis!$B$36*D8 -> 119213.75 | H8: =E8-G8 -> 128.25354
A9: Region 03 | B9: 18900 | C9: 305 | D9: 596 | E9: 121385 | G9: =Multicollinearity_Reg_Analysis!$B$37+Multicollinearity_Reg_Analysis!$B$34*B9+Multicollinearity_Reg_Analysis!$B$35*C9+Multicollinearity_Reg_Analysis!$B$36*D9 -> 122180.69 | H9: =E9-G9 -> -795.68756
A10: Region 04 | B10: 19600 | C10: 317 | D10: 617 | E10: 125740 | G10: =Multicollinearity_Reg_Analysis!$B$37+Multicollinearity_Reg_Analysis!$B$34*B10+Multicollinearity_Reg_Analysis!$B$35*C10+Multicollinearity_Reg_Analysis!$B$36*D10 -> 124467.27 | H10: =E10-G10 -> 1272.7257
A11: Region 05 | B11: 21050 | C11: 338 | D11: 662 | E11: 126882 | G11: =Multicollinearity_Reg_Analysis!$B$37+Multicollinearity_Reg_Analysis!$B$34*B11+Multicollinearity_Reg_Analysis!$B$35*C11+Multicollinearity_Reg_Analysis!$B$36*D11 -> 126751.11 | H11: =E11-G11 -> 130.893
A12: Region 06 | B12: 22500 | C12: 360 | D12: 699 | E12: 129225 | G12: =Multicollinearity_Reg_Analysis!$B$37+Multicollinearity_Reg_Analysis!$B$34*B12+Multicollinearity_Reg_Analysis!$B$35*C12+Multicollinearity_Reg_Analysis!$B$36*D12 -> 129411.99 | H12: =E12-G12 -> -186.98861
A13: Region 07 | B13: 23200 | C13: 376 | D13: 736 | E13: 134580 | G13: =Multicollinearity_Reg_Analysis!$B$37+Multicollinearity_Reg_Analysis!$B$34*B13+Multicollinearity_Reg_Analysis!$B$35*C13+Multicollinearity_Reg_Analysis!$B$36*D13 -> 134839.09 | H13: =E13-G13 -> -259.08805
A14: Region 08 | B14: 24650 | C14: 398 | D14: 774 | E14: 136622 | G14: =Multicollinearity_Reg_Analysis!$B$37+Multicollinearity_Reg_Analysis!$B$34*B14+Multicollinearity_Reg_Analysis!$B$35*C14+Multicollinearity_Reg_Analysis!$B$36*D14 -> 137533.98 | H14: =E14-G14 -> -911.97628
A15: Region 09 | B15: 26100 | C15: 422 | D15: 827 | E15: 142965 | G15: =Multicollinearity_Reg_Analysis!$B$37+Multicollinearity_Reg_Analysis!$B$34*B15+Multicollinearity_Reg_Analysis!$B$35*C15+Multicollinearity_Reg_Analysis!$B$36*D15 -> 142037.17 | H15: =E15-G15 -> 927.83286
A16: Region 10 | B16: 26800 | C16: 430 | D16: 836 | E16: 142120 | G16: =Multicollinearity_Reg_Analysis!$B$37+Multicollinearity_Reg_Analysis!$B$34*B16+Multicollinearity_Reg_Analysis!$B$35*C16+Multicollinearity_Reg_Analysis!$B$36*D16 -> 141319.27 | H16: =E16-G16 -> 800.73247
A17: Region 11 | B17: 28250 | C17: 453 | D17: 885 | E17: 144462 | G17: =Multicollinearity_Reg_Analysis!$B$37+Multicollinearity_Reg_Analysis!$B$34*B17+Multicollinearity_Reg_Analysis!$B$35*C17+Multicollinearity_Reg_Analysis!$B$36*D17 -> 145037.33 | H17: =E17-G17 -> -575.3302
A18: Region 12 | B18: 29700 | C18: 481 | D18: 937 | E18: 151805 | G18: =Multicollinearity_Reg_Analysis!$B$37+Multicollinearity_Reg_Analysis!$B$34*B18+Multicollinearity_Reg_Analysis!$B$35*C18+Multicollinearity_Reg_Analysis!$B$36*D18 -> 152102.92 | H18: =E18-G18 -> -297.92146
... A36: Region 30 | B36: 51300 | C36: 825 | D36: 1607 | E36: 207045 | G36: =Multicollinearity_Reg_Analysis!$B$37+Multicollinearity_Reg_Analysis!$B$34*B36+Multicollinearity_Reg_Analysis!$B$35*C36+Multicollinearity_Reg_Analysis!$B$36*D36 -> 206346.5 | H36: =E36-G36 -> 698.50406
A39: Regression Analysis Results
A41: Business question | B41: Model sales using paid media spend, campaign reach, and brand impressions, and assess whether the individual coefficients can be interpreted reliably.
A42: Model used | B42: Multiple linear regression with Sales as the continuous outcome and the three media measures as numeric predictors. The model supports combined prediction, while VIF and sensitivity tests assess separate coefficient interpretation.
A43: Data scope | B43: 30 regional observations; no missing or excluded rows.
A44: Estimated equation | B44: ="Sales = "&TEXT(Multicollinearity_Reg_Analysis!$B$37,"$#,##0")&IF(Multicollinearity_Reg_Analysis!$B$34<0," - "," + ")&TEXT(ABS(Multicollinearity_Reg_Analysis!$B$34),"0.000")&"×Paid Media Spend + "&TEXT(Multicollinearity_Reg_Analysis!$B$35,"$#,##0")&"×Reach (000s) + "&TEXT(Multicollinearity_Reg_Analysis!$B$36,"$#,##0")&"×Brand Impressions (000s)" -> Sales = $71,790 - 8.881×Paid Media Spend + $649×Reach (000s) + $34×Brand Impressions (000s)
A45: Combined prediction | B45: ="The model explains "&TEXT(Multicollinearity_Reg_Analysis!$B$8,"0.0%")&" of sales variation, with typical error of approximately "&TEXT(Multicollinearity_Reg_Analysis!$B$10,"$#,##0")&". Fitted sales are shown in G7:G36; use an approximate range of prediction ±"&TEXT(2*Multicollinearity_Reg_Analysis!$B$10,"$#,##0")&" for similar regions." -> The model explains 99.9% of sales variation, with typical error of approximately $745. Fitted sales are shown in G7:G36; use an approximate range of prediction ±$1,491 for similar regions.
A46: Coefficient reliability | B46: Individual coefficients are not reliably interpretable. All predictor correlations exceed 0.9999 and VIFs range from roughly 8,204 to 22,730, so the model cannot cleanly separate the effect of spend, reach, and impressions.
A47: Sensitivity evidence | B47: Each media variable has a positive relationship with sales when modeled alone, but paid media spend becomes negative when reach and impressions are included. This sign reversal is a multicollinearity artifact, not credible evidence that spending reduces sales.
A48: Validation | B48: ="A six-region holdout produced MAE of "&TEXT(Multicollinearity_Reg_Analysis!$B$12,"$#,##0")&" and RMSE of "&TEXT(Multicollinearity_Reg_Analysis!$B$13,"$#,##0")&". This supports limited prediction within the observed relationship, not channel attribution." -> A six-region holdout produced MAE of $565 and RMSE of $670. This supports limited prediction within the observed relationship, not channel attribution.
A49: Business recommendation | B49: Use one representative exposure metric or combine the three into a single media-intensity factor before interpreting drivers. The current model may be used cautiously for predicting similar regions, but not for allocating budget among spend, reach, and impressions.
A50: Model classification | B50: Use with caution
A51: Causality caution | B51: The model describes associations across regions and does not establish causal effects for any individual media measure.

Sheet Multicollinearity_Reg_Analysis
A1: Multicollinearity Regression Analysis
A3: Model Overview
A4: Outcome variable | B4: Sales
A5: Model type | B5: Multiple linear regression
A6: Predictor list (formula order) | B6: Paid Media Spend; Campaign Reach (000s); Brand Impressions (000s)
A7: Observations | B7: =COUNT(Multicollinearity!E7:E36) -> 30
A8: R-squared | B8: =INDEX(LINEST(Multicollinearity!E7:E36,Multicollinearity!B7:D36,TRUE,TRUE),3,1) -> 0.99937288
A9: Adjusted R-squared | B9: =1-(1-B8)*(B7-1)/(B7-3-1) -> 0.99930052
A10: Typical error | B10: =INDEX(LINEST(Multicollinearity!E7:E36,Multicollinearity!B7:D36,TRUE,TRUE),3,2) -> 745.29741
A11: Validation approach | B11: First 24 regions used for training; final 6 regions used as a sequential holdout.
A12: Holdout MAE | B12: =SUMPRODUCT(ABS(E61:E66))/COUNT(E61:E66) -> 564.83016
A13: Holdout RMSE | B13: =SQRT(SUMSQ(E61:E66)/COUNT(E61:E66)) -> 669.82168
A14: Model classification | B14: Use with caution
A17: Top Predictor Summary
A18: Rank | B18: Predictor | C18: Direction | D18: Coefficient | E18: Reliability | F18: Business Interpretation | G18: Notes
A19: 1 | B19: Paid Media Spend | C19: Negative in joint model | D19: =B34 -> -8.8811044 | E19: Not interpretable separately | F19: The negative joint coefficient should not be used to infer that additional paid media reduces sales. | G19: Positive when modeled alone; sign reverses due to predictor overlap.
A20: 2 | B20: Campaign Reach (000s) | C20: Positive in joint model | D20: =B35 -> 649.10175 | E20: Not interpretable separately | F20: The coefficient cannot isolate the value of reach because impressions and spend move almost identically. | G20: VIF exceeds 22,000.
A21: 3 | B21: Brand Impressions (000s) | C21: Positive in joint model | D21: =B36 -> 34.006609 | E21: Not interpretable separately | F21: The coefficient is highly uncertain after controlling for nearly duplicate media measures. | G21: Not statistically distinguishable from zero in the joint model.
A24: Diagnostics Summary
A25: Check | B25: Status | C25: Business Meaning
A26: Linearity | B26: No material concern | C26: The combined linear model fits the observed sales pattern closely.
A27: Outliers | B27: No material concern | C27: Maximum residual is about $1,273, which is not material relative to sales.
A28: Multicollinearity | B28: Material concern | C28: VIFs exceed 8,000 and pairwise correlations exceed 0.9999; individual effects are unstable.
A29: Validation | B29: Use with caution | C29: Holdout prediction is accurate, but the sequential split tests extrapolation along the same shared media trend.
A30: Data leakage | B30: No material concern | C30: The three media measures can be available before regional sales are measured.
A33: Coefficient | B33: Estimate | C33: Std. Error | D33: t-stat | E33: p-value | F33: 95% CI Low | G33: 95% CI High
A34: Paid Media Spend | B34: =INDEX(LINEST(Multicollinearity!E7:E36,Multicollinearity!B7:D36,TRUE,TRUE),1,3) -> -8.8811044 | C34: =INDEX(LINEST(Multicollinearity!E7:E36,Multicollinearity!B7:D36,TRUE,TRUE),2,3) -> 1.1841777 | D34: =B34/C34 -> -7.4998071 | E34: =_xlfn.T.DIST.2T(ABS(D34),B7-4) -> 5.8070988e-08 | F34: =B34-_xlfn.T.INV.2T(0.05,B7-4)*C34 -> -11.315217 | G34: =B34+_xlfn.T.INV.2T(0.05,B7-4)*C34 -> -6.4469923
A35: Campaign Reach (000s) | B35: =INDEX(LINEST(Multicollinearity!E7:E36,Multicollinearity!B7:D36,TRUE,TRUE),1,2) -> 649.10175 | C35: =INDEX(LINEST(Multicollinearity!E7:E36,Multicollinearity!B7:D36,TRUE,TRUE),2,2) -> 122.19507 | D35: =B35/C35 -> 5.3120127 | E35: =_xlfn.T.DIST.2T(ABS(D35),B7-4) -> 1.4777254e-05 | F35: =B35-_xlfn.T.INV.2T(0.05,B7-4)*C35 -> 397.92619 | G35: =B35+_xlfn.T.INV.2T(0.05,B7-4)*C35 -> 900.27731
A36: Brand Impressions (000s) | B36: =INDEX(LINEST(Multicollinearity!E7:E36,Multicollinearity!B7:D36,TRUE,TRUE),1,1) -> 34.006609 | C36: =INDEX(LINEST(Multicollinearity!E7:E36,Multicollinearity!B7:D36,TRUE,TRUE),2,1) -> 50.419911 | D36: =B36/C36 -> 0.67446785 | E36: =_xlfn.T.DIST.2T(ABS(D36),B7-4) -> 0.50596731 | F36: =B36-_xlfn.T.INV.2T(0.05,B7-4)*C36 -> -69.633003 | G36: =B36+_xlfn.T.INV.2T(0.05,B7-4)*C36 -> 137.64622
A37: Intercept | B37: =INDEX(LINEST(Multicollinearity!E7:E36,Multicollinearity!B7:D36,TRUE,TRUE),1,4) -> 71789.588 | C37: =INDEX(LINEST(Multicollinearity!E7:E36,Multicollinearity!B7:D36,TRUE,TRUE),2,4) -> 463.23325 | D37: =B37/C37 -> 154.97503 | E37: =_xlfn.T.DIST.2T(ABS(D37),B7-4) -> 4.2878181e-40 | F37: =B37-_xlfn.T.INV.2T(0.05,B7-4)*C37 -> 70837.399 | G37: =B37+_xlfn.T.INV.2T(0.05,B7-4)*C37 -> 72741.778
A40: Collinearity Diagnostics
A41: Predictor | B41: VIF | C41: Pairwise Correlation Notes
A42: Paid Media Spend | B42: 8203.7257 | C42: Corr. with Reach = 0.99994; with Impressions = 0.99991
A43: Campaign Reach | B43: 22729.927 | C43: Corr. with Impressions = 0.99997
A44: Brand Impressions | B44: 14709.921
A47: Coefficient Sensitivity
A48: Model Specification | B48: Paid Spend Coef. | C48: Reach Coef. | D48: Impressions Coef.
A49: Each predictor modeled alone | B49: 2.6581978 | C49: 164.86703 | D49: 84.561383
A50: All three predictors together | B50: =B34 -> -8.8811044 | C50: =B35 -> 649.10175 | D50: =B36 -> 34.006609
A51: Paid Spend + Reach | B51: -8.8744614 | C51: 714.98885
A52: Paid Spend + Impressions | B52: -5.1443733 | D52: 248.1214
A60: Region | B60: Actual Sales | C60: Predicted Sales | D60: Residual | E60: Absolute Error
A61: =Multicollinearity!A31 -> Region 25 | B61: =Multicollinearity!E31 -> 189820 | C61: =INDEX(LINEST(Multicollinearity!$E$7:$E$30,Multicollinearity!$B$7:$D$30,TRUE,TRUE),1,4)+INDEX(LINEST(Multicollinearity!$E$7:$E$30,Multicollinearity!$B$7:$D$30,TRUE,TRUE),1,3)*Multicollinearity!B31+INDEX(LINEST(Multicollinearity!$E$7:$E$30,Multicollinearity!$B$7:$D$30,TRUE,TRUE),1,2)*Multicollinearity!C31+INDEX(LINEST(Multicollinearity!$E$7:$E$30,Multicollinearity!$B$7:$D$30,TRUE,TRUE),1,1)*Multicollinearity!D31 -> 189774.11 | D61: =B61-C61 -> 45.887578 | E61: =ABS(D61) -> 45.887578
A62: =Multicollinearity!A32 -> Region 26 | B62: =Multicollinearity!E32 -> 192162 | C62: =INDEX(LINEST(Multicollinearity!$E$7:$E$30,Multicollinearity!$B$7:$D$30,TRUE,TRUE),1,4)+INDEX(LINEST(Multicollinearity!$E$7:$E$30,Multicollinearity!$B$7:$D$30,TRUE,TRUE),1,3)*Multicollinearity!B32+INDEX(LINEST(Multicollinearity!$E$7:$E$30,Multicollinearity!$B$7:$D$30,TRUE,TRUE),1,2)*Multicollinearity!C32+INDEX(LINEST(Multicollinearity!$E$7:$E$30,Multicollinearity!$B$7:$D$30,TRUE,TRUE),1,1)*Multicollinearity!D32 -> 192574.23 | D62: =B62-C62 -> -412.23373 | E62: =ABS(D62) -> 412.23373
A63: =Multicollinearity!A33 -> Region 27 | B63: =Multicollinearity!E33 -> 199505 | C63: =INDEX(LINEST(Multicollinearity!$E$7:$E$30,Multicollinearity!$B$7:$D$30,TRUE,TRUE),1,4)+INDEX(LINEST(Multicollinearity!$E$7:$E$30,Multicollinearity!$B$7:$D$30,TRUE,TRUE),1,3)*Multicollinearity!B33+INDEX(LINEST(Multicollinearity!$E$7:$E$30,Multicollinearity!$B$7:$D$30,TRUE,TRUE),1,2)*Multicollinearity!C33+INDEX(LINEST(Multicollinearity!$E$7:$E$30,Multicollinearity!$B$7:$D$30,TRUE,TRUE),1,1)*Multicollinearity!D33 -> 199802.16 | D63: =B63-C63 -> -297.16323 | E63: =ABS(D63) -> 297.16323
A64: =Multicollinearity!A34 -> Region 28 | B64: =Multicollinearity!E34 -> 199560 | C64: =INDEX(LINEST(Multicollinearity!$E$7:$E$30,Multicollinearity!$B$7:$D$30,TRUE,TRUE),1,4)+INDEX(LINEST(Multicollinearity!$E$7:$E$30,Multicollinearity!$B$7:$D$30,TRUE,TRUE),1,3)*Multicollinearity!B34+INDEX(LINEST(Multicollinearity!$E$7:$E$30,Multicollinearity!$B$7:$D$30,TRUE,TRUE),1,2)*Multicollinearity!C34+INDEX(LINEST(Multicollinearity!$E$7:$E$30,Multicollinearity!$B$7:$D$30,TRUE,TRUE),1,1)*Multicollinearity!D34 -> 200691.49 | D64: =B64-C64 -> -1131.4924 | E64: =ABS(D64) -> 1131.4924
A65: =Multicollinearity!A35 -> Region 29 | B65: =Multicollinearity!E35 -> 205902 | C65: =INDEX(LINEST(Multicollinearity!$E$7:$E$30,Multicollinearity!$B$7:$D$30,TRUE,TRUE),1,4)+INDEX(LINEST(Multicollinearity!$E$7:$E$30,Multicollinearity!$B$7:$D$30,TRUE,TRUE),1,3)*Multicollinearity!B35+INDEX(LINEST(Multicollinearity!$E$7:$E$30,Multicollinearity!$B$7:$D$30,TRUE,TRUE),1,2)*Multicollinearity!C35+INDEX(LINEST(Multicollinearity!$E$7:$E$30,Multicollinearity!$B$7:$D$30,TRUE,TRUE),1,1)*Multicollinearity!D35 -> 205043.58 | D65: =B65-C65 -> 858.42108 | E65: =ABS(D65) -> 858.42108
A66: =Multicollinearity!A36 -> Region 30 | B66: =Multicollinearity!E36 -> 207045 | C66: =INDEX(LINEST(Multicollinearity!$E$7:$E$30,Multicollinearity!$B$7:$D$30,TRUE,TRUE),1,4)+INDEX(LINEST(Multicollinearity!$E$7:$E$30,Multicollinearity!$B$7:$D$30,TRUE,TRUE),1,3)*Multicollinearity!B36+INDEX(LINEST(Multicollinearity!$E$7:$E$30,Multicollinearity!$B$7:$D$30,TRUE,TRUE),1,2)*Multicollinearity!C36+INDEX(LINEST(Multicollinearity!$E$7:$E$30,Multicollinearity!$B$7:$D$30,TRUE,TRUE),1,1)*Multicollinearity!D36 -> 206401.22 | D66: =B66-C66 -> 643.78298 | E66: =ABS(D66) -> 643.78298

Sheet Nonlinear_Risk
A1: Regression Diagnostic: Diminishing Marketing Returns
A2: Unsolved test case. Run the regression skill against this sheet and retain both mandatory Excel outputs.
A3: Business question | B3: Can one straight-line coefficient represent sales response across the full marketing investment range?
A4: Design note | B4: The relationship intentionally follows diminishing returns. The skill should inspect shape and residual behavior before accepting ordinary linear regression.
A6: Market | B6: Marketing Spend | C6: Sales | E6: Log-Model Sales | F6: Residual
A7: Market 01 | B7: 5000 | C7: 132777 | E7: =Nonlinear_Risk_Reg_Analysis!$B$35+Nonlinear_Risk_Reg_Analysis!$B$34*LN(B7) -> 108697.96 | F7: =C7-E7 -> 24079.042
A8: Market 02 | B8: 9500 | C8: 181338 | E8: =Nonlinear_Risk_Reg_Analysis!$B$35+Nonlinear_Risk_Reg_Analysis!$B$34*LN(B8) -> 181694.26 | F8: =C8-E8 -> -356.25592
A9: Market 03 | B9: 14000 | C9: 210032 | E9: =Nonlinear_Risk_Reg_Analysis!$B$35+Nonlinear_Risk_Reg_Analysis!$B$34*LN(B9) -> 225793.78 | F9: =C9-E9 -> -15761.776
A10: Market 04 | B10: 18500 | C10: 247897 | E10: =Nonlinear_Risk_Reg_Analysis!$B$35+Nonlinear_Risk_Reg_Analysis!$B$34*LN(B10) -> 257491.09 | F10: =C10-E10 -> -9594.0936
A11: Market 05 | B11: 23000 | C11: 266306 | E11: =Nonlinear_Risk_Reg_Analysis!$B$35+Nonlinear_Risk_Reg_Analysis!$B$34*LN(B11) -> 282252.19 | F11: =C11-E11 -> -15946.194
A12: Market 06 | B12: 27500 | C12: 294777 | E12: =Nonlinear_Risk_Reg_Analysis!$B$35+Nonlinear_Risk_Reg_Analysis!$B$34*LN(B12) -> 302574.33 | F12: =C12-E12 -> -7797.3251
A13: Market 07 | B13: 32000 | C13: 307277 | E13: =Nonlinear_Risk_Reg_Analysis!$B$35+Nonlinear_Risk_Reg_Analysis!$B$34*LN(B13) -> 319809.68 | F13: =C13-E13 -> -12532.683
A14: Market 08 | B14: 36500 | C14: 335334 | E14: =Nonlinear_Risk_Reg_Analysis!$B$35+Nonlinear_Risk_Reg_Analysis!$B$34*LN(B14) -> 334773.5 | F14: =C14-E14 -> 560.49538
A15: Market 09 | B15: 41000 | C15: 345934 | E15: =Nonlinear_Risk_Reg_Analysis!$B$35+Nonlinear_Risk_Reg_Analysis!$B$34*LN(B15) -> 347995.42 | F15: =C15-E15 -> -2061.4164
A16: Market 10 | B16: 45500 | C16: 367830 | E16: =Nonlinear_Risk_Reg_Analysis!$B$35+Nonlinear_Risk_Reg_Analysis!$B$34*LN(B16) -> 359839.01 | F16: =C16-E16 -> 7990.995
A17: Market 11 | B17: 50000 | C17: 372146 | E17: =Nonlinear_Risk_Reg_Analysis!$B$35+Nonlinear_Risk_Reg_Analysis!$B$34*LN(B17) -> 370564.7 | F17: =C17-E17 -> 1581.2977
A18: Market 12 | B18: 54500 | C18: 388180 | E18: =Nonlinear_Risk_Reg_Analysis!$B$35+Nonlinear_Risk_Reg_Analysis!$B$34*LN(B18) -> 380365.46 | F18: =C18-E18 -> 7814.5426
... A30: Market 24 | B30: 108500 | C30: 453142 | E30: =Nonlinear_Risk_Reg_Analysis!$B$35+Nonlinear_Risk_Reg_Analysis!$B$34*LN(B30) -> 458672.32 | F30: =C30-E30 -> -5530.3173
A33: Regression Analysis Results
A35: Business question | B35: How is marketing spend associated with sales, and can one constant straight-line coefficient represent the full investment range?
A36: Model used | B36: Logarithmic regression: Sales is modeled against the natural log of Marketing Spend. This specification fits the observed diminishing-return shape substantially better than ordinary straight-line regression.
A37: Data scope | B37: 24 market observations covering marketing spend from $5,000 to $108,500; no rows excluded.
A38: Key association | B38: ="A 10% increase in marketing spend is associated with approximately "&TEXT(Nonlinear_Risk_Reg_Analysis!$B$34*LN(1.1),"$#,##0")&" higher sales within the observed range." -> A 10% increase in marketing spend is associated with approximately $10,839 higher sales within the observed range.
A39: Estimated equation | B39: ="Estimated Sales = "&TEXT(Nonlinear_Risk_Reg_Analysis!$B$35,"$#,##0")&" + "&TEXT(Nonlinear_Risk_Reg_Analysis!$B$34,"$#,##0")&" × LN(Marketing Spend)" -> Estimated Sales = -$859,939 + $113,727 × LN(Marketing Spend)
A40: Diminishing returns | B40: ="An additional $1,000 is associated with about "&TEXT(Nonlinear_Risk_Reg_Analysis!$B$40,"$#,##0")&" at $10,000 spend, "&TEXT(Nonlinear_Risk_Reg_Analysis!$B$42,"$#,##0")&" at $50,000, and "&TEXT(Nonlinear_Risk_Reg_Analysis!$B$44,"$#,##0")&" at $100,000." -> An additional $1,000 is associated with about $10,839 at $10,000 spend, $2,252 at $50,000, and $1,132 at $100,000.
A41: Model reliability | B41: ="The log model explains "&TEXT(Nonlinear_Risk_Reg_Analysis!$B$8,"0.0%")&" of sales variation, with typical error of "&TEXT(Nonlinear_Risk_Reg_Analysis!$B$10,"$#,##0")&" and six-market holdout RMSE of "&TEXT(Nonlinear_Risk_Reg_Analysis!$B$13,"$#,##0")&"." -> The log model explains 99.0% of sales variation, with typical error of $9,479 and six-market holdout RMSE of $6,279.
A42: Linear-model risk | B42: ="A straight-line model explains only "&TEXT(Nonlinear_Risk_Reg_Analysis!$B$18,"0.0%")&" and has typical error of "&TEXT(Nonlinear_Risk_Reg_Analysis!$B$19,"$#,##0")&". Its residuals are systematically negative at low/high spend and positive in the middle." -> A straight-line model explains only 87.5% and has typical error of $33,525. Its residuals are systematically negative at low/high spend and positive in the middle.
A43: Prediction or scenario result | B43: ="Fitted values are shown in E7:E30. For scenarios inside the observed spend range, use an approximate range of predicted sales ±"&TEXT(2*Nonlinear_Risk_Reg_Analysis!$B$10,"$#,##0")&"." -> Fitted values are shown in E7:E30. For scenarios inside the observed spend range, use an approximate range of predicted sales ±$18,957.
A44: Business recommendation | B44: Use the logarithmic model for directional spend scenarios within the historical range. Do not use a single constant sales-per-dollar coefficient or extrapolate beyond the observed spend range without new validation.
A45: Model classification | B45: Ready for decision support
A46: Causality caution | B46: The model estimates an association across markets; it does not prove that additional marketing spend caused the sales differences.

Sheet Nonlinear_Risk_Reg_Analysis
A1: Nonlinear Risk Regression Analysis
A3: Model Overview
A4: Outcome variable | B4: Sales
A5: Selected model | B5: Logarithmic regression: Sales = Intercept + Coefficient × LN(Marketing Spend)
A6: Predictor list (formula order) | B6: LN(Marketing Spend)
A7: Observations | B7: =COUNT(Nonlinear_Risk!B7:B30) -> 24
A8: R-squared | B8: =RSQ(Nonlinear_Risk!C7:C30,LN(Nonlinear_Risk!B7:B30)) -> 0.98998946
A9: Adjusted R-squared | B9: =1-(1-B8)*(B7-1)/(B7-2) -> 0.98953443
A10: Typical error | B10: =STEYX(Nonlinear_Risk!C7:C30,LN(Nonlinear_Risk!B7:B30)) -> 9478.547
A11: Validation approach | B11: First 18 markets used for training; final 6 markets used as a sequential spend-range holdout.
A12: Holdout MAE | B12: =SUMPRODUCT(ABS(E77:E82))/COUNT(E77:E82) -> 5286.9634
A13: Holdout RMSE | B13: =SQRT(SUMSQ(E77:E82)/COUNT(E77:E82)) -> 6279.4092
A14: Model classification | B14: Ready for decision support
A17: Model Comparison
A18: Linear R-squared | B18: =RSQ(Nonlinear_Risk!C7:C30,Nonlinear_Risk!B7:B30) -> 0.87476838
A19: Linear typical error | B19: =STEYX(Nonlinear_Risk!C7:C30,Nonlinear_Risk!B7:B30) -> 33525.092
A20: Linear holdout RMSE | B20: 84001.66
A21: Log R-squared | B21: =B8 -> 0.98998946
A22: Log typical error | B22: =B10 -> 9478.547
A23: Log holdout RMSE | B23: =B13 -> 6279.4092
A26: Top Predictor Summary
A27: Rank | B27: Predictor | C27: Direction | D27: Coefficient | E27: Reliability | F27: Business Interpretation | G27: Notes
A28: 1 | B28: LN(Marketing Spend) | C28: Positive, diminishing returns | D28: =B34 -> 113727.28 | E28: Verified estimate | F28: ="A 10% increase in spend is associated with approximately "&TEXT(D28*LN(1.1),"$#,##0")&" higher sales." -> A 10% increase in spend is associated with approximately $10,839 higher sales. | G28: Marginal sales per additional dollar declines as the spend base increases.
A31: Diagnostics Summary
A32: Check | B32: Status | C32: Business Meaning
A33: Linearity | B33: Material concern for raw linear model | C33: A straight line produces a curved residual pattern and substantially worse holdout error.
A34: Log coefficient | B34: =SLOPE(Nonlinear_Risk!C7:C30,LN(Nonlinear_Risk!B7:B30)) -> 113727.28 | C34: =INDEX(LINEST(Nonlinear_Risk!C7:C30,LN(Nonlinear_Risk!B7:B30),TRUE,TRUE),2,1) -> 2438.186 | D34: =B34/C34 -> 46.644219 | E34: =_xlfn.T.DIST.2T(ABS(D34),B7-2) -> 1.7093487e-23 | F34: =B34-_xlfn.T.INV.2T(0.05,B7-2)*C34 -> 108670.79 | G34: =B34+_xlfn.T.INV.2T(0.05,B7-2)*C34 -> 118783.77
A35: Log intercept | B35: =INTERCEPT(Nonlinear_Risk!C7:C30,LN(Nonlinear_Risk!B7:B30)) -> -859939.27
A37: Incremental $1,000 Scenarios
A38: Starting Spend | B38: Associated Sales Increase
A40: 10000 | B40: =$B$34*LN((A40+1000)/A40) -> 10839.368
A41: 25000 | B41: =$B$34*LN((A41+1000)/A41) -> 4460.4651
A42: 50000 | B42: =$B$34*LN((A42+1000)/A42) -> 2252.099
A43: 75000 | B43: =$B$34*LN((A43+1000)/A43) -> 1506.3436
A44: 100000 | B44: =$B$34*LN((A44+1000)/A44) -> 1131.6241
A47: Residual Diagnostics
A48: Market | B48: Spend | C48: Actual Sales | D48: Log Prediction | E48: Residual
A49: =Nonlinear_Risk!A7 -> Market 01 | B49: =Nonlinear_Risk!B7 -> 5000 | C49: =Nonlinear_Risk!C7 -> 132777 | D49: =$B$35+$B$34*LN(B49) -> 108697.96 | E49: =C49-D49 -> 24079.042
A50: =Nonlinear_Risk!A8 -> Market 02 | B50: =Nonlinear_Risk!B8 -> 9500 | C50: =Nonlinear_Risk!C8 -> 181338 | D50: =$B$35+$B$34*LN(B50) -> 181694.26 | E50: =C50-D50 -> -356.25592
A51: =Nonlinear_Risk!A9 -> Market 03 | B51: =Nonlinear_Risk!B9 -> 14000 | C51: =Nonlinear_Risk!C9 -> 210032 | D51: =$B$35+$B$34*LN(B51) -> 225793.78 | E51: =C51-D51 -> -15761.776
A52: =Nonlinear_Risk!A10 -> Market 04 | B52: =Nonlinear_Risk!B10 -> 18500 | C52: =Nonlinear_Risk!C10 -> 247897 | D52: =$B$35+$B$34*LN(B52) -> 257491.09 | E52: =C52-D52 -> -9594.0936
A53: =Nonlinear_Risk!A11 -> Market 05 | B53: =Nonlinear_Risk!B11 -> 23000 | C53: =Nonlinear_Risk!C11 -> 266306 | D53: =$B$35+$B$34*LN(B53) -> 282252.19 | E53: =C53-D53 -> -15946.194
A54: =Nonlinear_Risk!A12 -> Market 06 | B54: =Nonlinear_Risk!B12 -> 27500 | C54: =Nonlinear_Risk!C12 -> 294777 | D54: =$B$35+$B$34*LN(B54) -> 302574.33 | E54: =C54-D54 -> -7797.3251
A55: =Nonlinear_Risk!A13 -> Market 07 | B55: =Nonlinear_Risk!B13 -> 32000 | C55: =Nonlinear_Risk!C13 -> 307277 | D55: =$B$35+$B$34*LN(B55) -> 319809.68 | E55: =C55-D55 -> -12532.683
A56: =Nonlinear_Risk!A14 -> Market 08 | B56: =Nonlinear_Risk!B14 -> 36500 | C56: =Nonlinear_Risk!C14 -> 335334 | D56: =$B$35+$B$34*LN(B56) -> 334773.5 | E56: =C56-D56 -> 560.49538
A57: =Nonlinear_Risk!A15 -> Market 09 | B57: =Nonlinear_Risk!B15 -> 41000 | C57: =Nonlinear_Risk!C15 -> 345934 | D57: =$B$35+$B$34*LN(B57) -> 347995.42 | E57: =C57-D57 -> -2061.4164
A58: =Nonlinear_Risk!A16 -> Market 10 | B58: =Nonlinear_Risk!B16 -> 45500 | C58: =Nonlinear_Risk!C16 -> 367830 | D58: =$B$35+$B$34*LN(B58) -> 359839.01 | E58: =C58-D58 -> 7990.995
A59: =Nonlinear_Risk!A17 -> Market 11 | B59: =Nonlinear_Risk!B17 -> 50000 | C59: =Nonlinear_Risk!C17 -> 372146 | D59: =$B$35+$B$34*LN(B59) -> 370564.7 | E59: =C59-D59 -> 1581.2977
A60: =Nonlinear_Risk!A18 -> Market 12 | B60: =Nonlinear_Risk!B18 -> 54500 | C60: =Nonlinear_Risk!C18 -> 388180 | D60: =$B$35+$B$34*LN(B60) -> 380365.46 | E60: =C60-D60 -> 7814.5426
... A72: =Nonlinear_Risk!A30 -> Market 24 | B72: =Nonlinear_Risk!B30 -> 108500 | C72: =Nonlinear_Risk!C30 -> 453142 | D72: =$B$35+$B$34*LN(B72) -> 458672.32 | E72: =C72-D72 -> -5530.3173
A76: Holdout Market | B76: Actual Sales | C76: Predicted Sales | D76: Residual | E76: Absolute Error
A77: =Nonlinear_Risk!A25 -> Market 19 | B77: =Nonlinear_Risk!C25 -> 428642 | C77: =INTERCEPT(Nonlinear_Risk!$C$7:$C$24,LN(Nonlinear_Risk!$B$7:$B$24))+SLOPE(Nonlinear_Risk!$C$7:$C$24,LN(Nonlinear_Risk!$B$7:$B$24))*LN(Nonlinear_Risk!B25) -> 434295.08 | D77: =B77-C77 -> -5653.0836 | E77: =ABS(D77) -> 5653.0836
A78: =Nonlinear_Risk!A26 -> Market 20 | B78: =Nonlinear_Risk!C26 -> 442438 | C78: =INTERCEPT(Nonlinear_Risk!$C$7:$C$24,LN(Nonlinear_Risk!$B$7:$B$24))+SLOPE(Nonlinear_Risk!$C$7:$C$24,LN(Nonlinear_Risk!$B$7:$B$24))*LN(Nonlinear_Risk!B26) -> 440168.67 | D78: =B78-C78 -> 2269.3333 | E78: =ABS(D78) -> 2269.3333
A79: =Nonlinear_Risk!A27 -> Market 21 | B79: =Nonlinear_Risk!C27 -> 440453 | C79: =INTERCEPT(Nonlinear_Risk!$C$7:$C$24,LN(Nonlinear_Risk!$B$7:$B$24))+SLOPE(Nonlinear_Risk!$C$7:$C$24,LN(Nonlinear_Risk!$B$7:$B$24))*LN(Nonlinear_Risk!B27) -> 445757.16 | D79: =B79-C79 -> -5304.1635 | E79: =ABS(D79) -> 5304.1635
A80: =Nonlinear_Risk!A28 -> Market 22 | B80: =Nonlinear_Risk!C28 -> 451242 | C80: =INTERCEPT(Nonlinear_Risk!$C$7:$C$24,LN(Nonlinear_Risk!$B$7:$B$24))+SLOPE(Nonlinear_Risk!$C$7:$C$24,LN(Nonlinear_Risk!$B$7:$B$24))*LN(Nonlinear_Risk!B28) -> 451086.97 | D80: =B80-C80 -> 155.02807 | E80: =ABS(D80) -> 155.02807
A81: =Nonlinear_Risk!A29 -> Market 23 | B81: =Nonlinear_Risk!C29 -> 445758 | C81: =INTERCEPT(Nonlinear_Risk!$C$7:$C$24,LN(Nonlinear_Risk!$B$7:$B$24))+SLOPE(Nonlinear_Risk!$C$7:$C$24,LN(Nonlinear_Risk!$B$7:$B$24))*LN(Nonlinear_Risk!B29) -> 456180.99 | D81: =B81-C81 -> -10422.985 | E81: =ABS(D81) -> 10422.985
A82: =Nonlinear_Risk!A30 -> Market 24 | B82: =Nonlinear_Risk!C30 -> 453142 | C82: =INTERCEPT(Nonlinear_Risk!$C$7:$C$24,LN(Nonlinear_Risk!$B$7:$B$24))+SLOPE(Nonlinear_Risk!$C$7:$C$24,LN(Nonlinear_Risk!$B$7:$B$24))*LN(Nonlinear_Risk!B30) -> 461059.19 | D82: =B82-C82 -> -7917.1865 | E82: =ABS(D82) -> 7917.1865

Sheet Binary_Outcome
A1: Method Selection: Customer Churn
A2: Unsolved test case. Run the regression skill against this sheet and retain both mandatory Excel outputs.
A3: Business question | B3: Which customer characteristics are associated with the probability of churn?
A4: Design note | B4: The outcome is binary (0/1). This is a deliberate method-selection gate: ordinary linear regression should not be used.
A6: Customer ID | B6: Service Tickets | C6: Tenure (Months) | D6: Monthly Spend | E6: Churn Flag (1=Yes) | F6: Predicted Churn Probability | G6: Risk Band
A7: CUST-1001 | B7: 0 | C7: 2 | D7: 90 | E7: 0 | F7: 0.00023439073 | G7: Low
A8: CUST-1002 | B8: 1 | C8: 3 | D8: 125 | E8: 0 | F8: 0.0027692006 | G8: Low
A9: CUST-1003 | B9: 2 | C9: 4 | D9: 160 | E9: 0 | F9: 0.031843498 | G9: Low
A10: CUST-1004 | B10: 3 | C10: 5 | D10: 195 | E10: 1 | F10: 0.28035579 | G10: Low
A11: CUST-1005 | B11: 4 | C11: 6 | D11: 230 | E11: 0 | F11: 0.8218842 | G11: High
A12: CUST-1006 | B12: 5 | C12: 7 | D12: 265 | E12: 1 | F12: 0.98203195 | G12: High
A13: CUST-1007 | B13: 6 | C13: 8 | D13: 300 | E13: 1 | F13: 0.99845763 | G13: High
A14: CUST-1008 | B14: 0 | C14: 9 | D14: 335 | E14: 0 | F14: 6.7636465e-08 | G14: Low
A15: CUST-1009 | B15: 1 | C15: 10 | D15: 370 | E15: 0 | F15: 8.0111906e-07 | G15: Low
A16: CUST-1010 | B16: 2 | C16: 11 | D16: 405 | E16: 0 | F16: 9.4887667e-06 | G16: Low
A17: CUST-1011 | B17: 3 | C17: 12 | D17: 90 | E17: 0 | F17: 0.017900288 | G17: Low
A18: CUST-1012 | B18: 4 | C18: 13 | D18: 125 | E18: 0 | F18: 0.17755328 | G18: Low
... A34: CUST-1028 | B34: 6 | C34: 11 | D34: 335 | E34: 1 | F34: 0.98196796 | G34: High
A37: Regression Analysis Results
A38: Business question | B38: Predict customer churn from service tickets, tenure, and monthly spend.
A39: Model used | B39: Logistic regression because churn is binary (0/1); ordinary linear regression is not appropriate.
A40: Data scope | B40: 28 customers; 10 churn events (35.7%); no excluded rows.
A41: Key driver 1 | B41: Service tickets: odds multiply by 37.95 for each additional ticket, holding other variables constant.
A42: Key driver 2 | B42: Tenure: odds multiply by 0.52 for each additional month, holding other variables constant.
A43: Key driver 3 | B43: Monthly spend: odds multiply by 0.86 for each additional $10, holding other variables constant.
A44: Estimated equation | B44: logit(P(churn)) = -5.739 + 3.636×Tickets - 0.656×Tenure - 0.0145×Monthly Spend
A45: Prediction result | B45: Probabilities and screening risk bands are written for all customers in columns F:G; highest estimated risk is CUST-1021 at above 99%, but this extreme estimate is unstable in the small sample.
A46: Model reliability | B46: In-sample AUC 0.983 and accuracy 92.9%; leave-one-out AUC 0.844, accuracy 85.7%, Brier score 0.103.
A47: Limitations and diagnostics | B47: Only 10 churn events for 3 predictors (3.3 events per predictor). Coefficient inference is unstable; validation is limited to leave-one-out resampling.
A48: Business recommendation | B48: Use the probabilities to prioritize review, not automated retention decisions. Collect more churn events and validate on a future customer cohort before deployment.
A49: Model classification | B49: Do not rely on this model yet

Sheet Binary_Outcome_Reg_Analysis
A1: Logistic Regression Technical Summary
A2: Outcome variable | B2: Churn Flag (1=Yes)
A3: Model type | B3: Multiple logistic regression
A4: Predictor formula order | B4: Service Tickets; Tenure (Months); Monthly Spend
A5: Observations | B5: 28
A6: Churn events | B6: 10
A7: Events per predictor | B7: 3.3333333
A8: In-sample AUC | B8: 0.98333333
A9: In-sample accuracy (0.50 threshold) | B9: 0.92857143
A10: LOOCV AUC | B10: 0.84444444
A11: LOOCV accuracy (0.50 threshold) | B11: 0.85714286
A12: LOOCV sensitivity | B12: 0.8
A13: LOOCV specificity | B13: 0.88888889
A14: LOOCV Brier score | B14: 0.10269708
A15: Validation approach | B15: Leave-one-out cross-validation; no independent future holdout available
A16: Model classification | B16: Do not rely on this model yet
A18: Predictor | B18: Coefficient | C18: Std. Error | D18: Odds Ratio | E18: Wald p-value | F18: Reliability | G18: Business interpretation
A19: Intercept | B19: -5.7386973 | C19: 5.0577622 | D19: 0.0032189589 | E19: 0.25652971 | F19: Use with caution | G19: Baseline log-odds; not meaningful at zero values outside practical context.
A20: Service Tickets | B20: 3.6362676 | C20: 2.2119351 | D20: 37.949928 | E20: 0.10019052 | F20: Use with caution | G20: Each additional ticket multiplies estimated churn odds by 37.95, holding other predictors constant.
A21: Tenure (Months) | B21: -0.65553922 | C21: 0.57921239 | D21: 0.51916204 | E21: 0.25772828 | F21: Use with caution | G21: Each additional tenure month multiplies estimated churn odds by 0.52, holding other predictors constant.
A22: Monthly Spend | B22: -0.01453901 | C22: 0.024964007 | D22: 0.98556617 | E22: 0.56029781 | F22: Use with caution | G22: Each additional $10 multiplies estimated churn odds by 0.86, holding other predictors constant.
A24: Rank | B24: Predictor | C24: Direction | D24: Odds Ratio | E24: Reliability | F24: Business Interpretation | G24: Notes
A25: 1 | B25: Service Tickets | C25: Positive | D25: 37.949928 | E25: Use with caution | F25: Ticket volume is the strongest operational risk signal in this small sample. | G25: Association, not causation
A26: 2 | B26: Tenure (Months) | C26: Negative | D26: 0.51916204 | E26: Use with caution | F26: Tenure changes estimated churn odds after controlling for tickets and spend. | G26: Association, not causation
A27: 3 | B27: Monthly Spend | C27: Negative | D27: 0.86468492 | E27: Use with caution | F27: Spend changes estimated churn odds, but the small event count limits stability. | G27: Association, not causation
A29: Check | B29: Status | C29: Business Meaning
A30: Outcome suitability | B30: No material concern | C30: Logistic regression matches the binary 0/1 churn outcome.
A31: Sample size / events | B31: Material concern | C31: 10 events for 3 predictors is too limited for stable deployment-grade estimates.
A32: Multicollinearity | B32: No material concern | C32: Maximum absolute predictor correlation is 0.200.
A33: Linearity in the logit | B33: Use with caution | C33: Not fully testable with this small dataset; continuous predictors may need nonlinear terms in a larger sample.
A34: Outliers / separation | B34: Use with caution | C34: Small cells and strong predictor patterns may create unstable maximum-likelihood estimates.
A35: Validation | B35: Material concern | C35: LOOCV is informative but no independent future cohort is available.
A36: Data leakage | B36: No material concern | C36: All listed predictors can be known before the churn outcome if captured at scoring time.
A38: Customer ID | B38: Actual Churn | C38: Predicted Probability | D38: LOOCV Probability | E38: Predicted Class | F38: Risk Band
A39: CUST-1001 | B39: 0 | C39: 0.00023439073 | D39: 0.00023549428 | E39: 0 | F39: Low
A40: CUST-1002 | B40: 0 | C40: 0.0027692006 | D40: 0.0028599727 | E40: 0 | F40: Low
A41: CUST-1003 | B41: 0 | C41: 0.031843498 | D41: 0.038721474 | E41: 0 | F41: Low
A42: CUST-1004 | B42: 1 | C42: 0.28035579 | D42: 4.2715305e-16 | E42: 0 | F42: Low
A43: CUST-1005 | B43: 0 | C43: 0.8218842 | D43: 1 | E43: 1 | F43: High
A44: CUST-1006 | B44: 1 | C44: 0.98203195 | D44: 0.98011048 | E44: 1 | F44: High
A45: CUST-1007 | B45: 1 | C45: 0.99845763 | D45: 0.99843066 | E45: 1 | F45: High
A46: CUST-1008 | B46: 0 | C46: 6.7636465e-08 | D46: 6.7627236e-08 | E46: 0 | F46: Low
A47: CUST-1009 | B47: 0 | C47: 8.0111906e-07 | D47: 8.0121135e-07 | E47: 0 | F47: Low
A48: CUST-1010 | B48: 0 | C48: 9.4887667e-06 | D48: 9.498594e-06 | E48: 0 | F48: Low
A49: CUST-1011 | B49: 0 | C49: 0.017900288 | D49: 0.019803266 | E49: 0 | F49: Low
A50: CUST-1012 | B50: 0 | C50: 0.17755328 | D50: 0.29287808 | E50: 0 | F50: Low
... A66: CUST-1028 | B66: 1 | C66: 0.98196796 | D66: 0.98000875 | E66: 1 | F66: High

Sheet Time_Leakage
A1: Prediction Diagnostic: Month-End Data Leakage
A2: Unsolved test case. Run the regression skill against this sheet and retain both mandatory Excel outputs.
A3: Business question | B3: Can the model estimate monthly sales using only information available
A4: Design note | B4: Month-end sales adjustment is calculated after actual sales are known. It is intentionally leaked and must be excluded from a planning model
A6: Month | B6: Marketing Spend | C6: Pre-Month-End Sales Calls | D6: Month-End Sales Adjustment | E6: Actual Sales | F6: Valid Planning Prediction | G6: Residual | H6: Leaked Model Prediction
A7: 45292 | B7: 14000 | C7: 45 | D7: 18626 | E7: 117100 | F7: =Time_Leakage_Reg_Analysis!$K$14+Time_Leakage_Reg_Analysis!$K$12*B7+Time_Leakage_Reg_Analysis!$K$13*C7 -> 120397.02 | G7: =E7-F7 -> -3297.0225 | H7: 117200.05
A8: 45323 | B8: 16200 | C8: 52 | D8: 21605 | E8: 134560 | F8: =Time_Leakage_Reg_Analysis!$K$14+Time_Leakage_Reg_Analysis!$K$12*B8+Time_Leakage_Reg_Analysis!$K$13*C8 -> 131794.34 | G8: =E8-F8 -> 2765.6614 | H8: 134629.78
A9: 45352 | B9: 18400 | C9: 59 | D9: 22678 | E9: 142020 | F9: =Time_Leakage_Reg_Analysis!$K$14+Time_Leakage_Reg_Analysis!$K$12*B9+Time_Leakage_Reg_Analysis!$K$13*C9 -> 143191.65 | G9: =E9-F9 -> -1171.6547 | H9: 142026.47
A10: 45383 | B10: 20600 | C10: 66 | D10: 25319 | E10: 157680 | F10: =Time_Leakage_Reg_Analysis!$K$14+Time_Leakage_Reg_Analysis!$K$12*B10+Time_Leakage_Reg_Analysis!$K$13*C10 -> 154588.97 | G10: =E10-F10 -> 3091.0292 | H10: 157677
A11: 45413 | B11: 22800 | C11: 73 | D11: 26296 | E11: 165040 | F11: =Time_Leakage_Reg_Analysis!$K$14+Time_Leakage_Reg_Analysis!$K$12*B11+Time_Leakage_Reg_Analysis!$K$13*C11 -> 165986.29 | G11: =E11-F11 -> -946.28696 | H11: 164568.35
A12: 45444 | B12: 25000 | C12: 80 | D12: 28619 | E12: 178400 | F12: =Time_Leakage_Reg_Analysis!$K$14+Time_Leakage_Reg_Analysis!$K$12*B12+Time_Leakage_Reg_Analysis!$K$13*C12 -> 177383.6 | G12: =E12-F12 -> 1016.3969 | H12: 178544.95
A13: 45474 | B13: 27200 | C13: 87 | D13: 29405 | E13: 184060 | F13: =Time_Leakage_Reg_Analysis!$K$14+Time_Leakage_Reg_Analysis!$K$12*B13+Time_Leakage_Reg_Analysis!$K$13*C13 -> 188780.92 | G13: =E13-F13 -> -4720.9192 | H13: 184430.9
A14: 45505 | B14: 29400 | C14: 94 | D14: 32333 | E14: 201520 | F14: =Time_Leakage_Reg_Analysis!$K$14+Time_Leakage_Reg_Analysis!$K$12*B14+Time_Leakage_Reg_Analysis!$K$13*C14 -> 200178.24 | G14: =E14-F14 -> 1341.7647 | H14: 201592.17
A15: 45536 | B15: 14000 | C15: 101 | D15: 24597 | E15: 154420 | F15: =Time_Leakage_Reg_Analysis!$K$14+Time_Leakage_Reg_Analysis!$K$12*B15+Time_Leakage_Reg_Analysis!$K$13*C15 -> 155482.11 | G15: =E15-F15 -> -1062.1061 | H15: 154290.51
A16: 45566 | B16: 16200 | C16: 45 | D16: 21038 | E16: 131020 | F16: =Time_Leakage_Reg_Analysis!$K$14+Time_Leakage_Reg_Analysis!$K$12*B16+Time_Leakage_Reg_Analysis!$K$13*C16 -> 127408.7 | G16: =E16-F16 -> 3611.2968 | H16: 130937.69
A17: 45597 | B17: 18400 | C17: 52 | D17: 22096 | E17: 138380 | F17: =Time_Leakage_Reg_Analysis!$K$14+Time_Leakage_Reg_Analysis!$K$12*B17+Time_Leakage_Reg_Analysis!$K$13*C17 -> 138806.02 | G17: =E17-F17 -> -426.01928 | H17: 138255.42
A18: 45627 | B18: 20600 | C18: 59 | D18: 24368 | E18: 151740 | F18: =Time_Leakage_Reg_Analysis!$K$14+Time_Leakage_Reg_Analysis!$K$12*B18+Time_Leakage_Reg_Analysis!$K$13*C18 -> 150203.34 | G18: =E18-F18 -> 1536.6646 | H18: 151963.56
... A30: 45992 | B30: 29400 | C30: 80 | D30: 30816 | E30: 192040 | F30: =Time_Leakage_Reg_Analysis!$K$14+Time_Leakage_Reg_Analysis!$K$12*B30+Time_Leakage_Reg_Analysis!$K$13*C30 -> 191406.96 | G30: =E30-F30 -> 633.03558 | H30: 192191.9
A33: Regression Analysis Results
A34: Business question | B34: Build a monthly sales planning model using only information available before month end.
A35: Model used | B35: Multiple linear regression of Actual Sales on Marketing Spend and Pre-Month-End Sales Calls. Month-End Sales Adjustment is excluded because it is known after actual sales.
A36: Data scope | B36: 24 monthly observations from Jan-2024 through Dec-2025; final 6 months reserved for time-ordered validation; no excluded rows.
A37: Key driver 1 | B37: Marketing spend: each additional $1,000 is associated with approximately $3,187 in monthly sales, holding pre-month-end calls constant.
A38: Key driver 2 | B38: Pre-month-end sales calls: each additional call is associated with approximately $627 in monthly sales, holding marketing spend constant.
A39: Estimated equation | B39: Planned Sales = $47,584 + 3.187×Marketing Spend + $627×Pre-Month-End Calls
A40: Prediction result | B40: Use the editable scenario below. A practical planning range is the point estimate ± about $4,994, based on the model's historical typical error.
A41: Model reliability | B41: Full-sample adjusted R² 98.7%; typical error $2,548. Six-month holdout RMSE $2,346 and MAPE 1.4%.
A42: Limitations and diagnostics | B42: Only 24 months of history. Marketing spend and calls correlation is 0.30. The leaked model appears stronger (holdout RMSE $265) but cannot be used for planning.
A43: Business recommendation | B43: Use only marketing spend and pre-month-end call assumptions for planning. Refresh and revalidate monthly; never include the month-end adjustment in a forward forecast.
A44: Model classification | B44: Use with caution
A47: Monthly Sales Planning Scenario
A48: Planned Marketing Spend | B48: 29400
A49: Planned Pre-Month-End Calls | B49: 80
A50: Estimated Monthly Sales | B50: =Time_Leakage_Reg_Analysis!$K$14+Time_Leakage_Reg_Analysis!$K$12*B48+Time_Leakage_Reg_Analysis!$K$13*B49 -> 191406.96
A51: Planning Range - Low | B51: =B50-1.96*Time_Leakage_Reg_Analysis!$K$17 -> 186413.08
A52: Planning Range - High | B52: =B50+1.96*Time_Leakage_Reg_Analysis!$K$17 -> 196400.85
A53: Important | B53: Inputs must be known before month end; do not use Month-End Sales Adjustment.

Sheet Time_Leakage_Reg_Analysis
A1: Monthly Sales Planning Model - Technical Summary | J1: Descriptive Sales Statistics
A2: Outcome variable | B2: Actual Sales | J2: Mean monthly sales | K2: 160835.83
A3: Selected model | B3: Multiple linear regression using pre-month-end predictors only | J3: Median monthly sales | K3: 157540
A4: Predictor formula order | B4: Marketing Spend; Pre-Month-End Sales Calls | J4: Minimum monthly sales | K4: 117100
A5: Excluded predictor | B5: Month-End Sales Adjustment — confirmed data leakage | J5: Maximum monthly sales | K5: 201520
A6: Observations | B6: 24 | J6: Historical range | K6: 84420
A7: Training / validation split | B7: First 18 months / final 6 months | J7: Selected model equation | K7: Sales = 47584 + 3.187×Marketing + 627×Calls
A8: R-squared | B8: 0.98830922 | J8: Approx. 95% planning error band | K8: 4993.8884
A9: Adjusted R-squared | B9: 0.98719581 | J9: Leakage warning | K9: Do not include Month-End Sales Adjustment in forward planning
A10: Typical error (residual standard error) | B10: 2547.9022
A11: Holdout MAE | B11: 2099.5454 | J11: Excel-Native Model Audit
A12: Holdout RMSE | B12: 2345.684 | J12: Marketing Spend coefficient | K12: =INDEX(LINEST(Time_Leakage!$E$7:$E$30,Time_Leakage!$B$7:$C$30,TRUE,TRUE),1,2) -> 3.1871276
A13: Holdout MAPE | B13: 0.013824134 | J13: Pre-Month-End Calls coefficient | K13: =INDEX(LINEST(Time_Leakage!$E$7:$E$30,Time_Leakage!$B$7:$C$30,TRUE,TRUE),1,1) -> 626.51935
A14: Validation approach | B14: Time-ordered holdout using Jul-2025 through Dec-2025 | J14: Intercept | K14: =INDEX(LINEST(Time_Leakage!$E$7:$E$30,Time_Leakage!$B$7:$C$30,TRUE,TRUE),1,3) -> 47583.866
A15: Model classification | B15: Use with caution | J15: R-squared | K15: =INDEX(LINEST(Time_Leakage!$E$7:$E$30,Time_Leakage!$B$7:$C$30,TRUE,TRUE),3,1) -> 0.98830922
J16: Adjusted R-squared | K16: =1-(1-K15)*(COUNT(Time_Leakage!$E$7:$E$30)-1)/(COUNT(Time_Leakage!$E$7:$E$30)-2-1) -> 0.98719581
A17: Rank | B17: Predictor | C17: Direction | D17: Coefficient | E17: Reliability | F17: Business Interpretation | G17: Notes | J17: Typical error | K17: =INDEX(LINEST(Time_Leakage!$E$7:$E$30,Time_Leakage!$B$7:$C$30,TRUE,TRUE),3,2) -> 2547.9022
A18: 1 | B18: Marketing Spend | C18: Positive | D18: 3.1871276 | E18: Verified estimate | F18: Each additional $1,000 is associated with about $3187 in sales, holding calls constant. | G18: Association, not causation | J18: Formula method | K18: INDEX(LINEST(Actual Sales, pre-month-end predictors, TRUE, TRUE))
A19: 2 | B19: Pre-Month-End Sales Calls | C19: Positive | D19: 626.51935 | E19: Verified estimate | F19: Each additional call is associated with about $627 in sales, holding marketing spend constant. | G19: Available before month end
A21: Check | B21: Status | C21: Business Meaning
A22: Linearity | B22: No material concern | C22: Residual correlation with time is 0.05; monitor for drift.
A23: Outliers | B23: No material concern | C23: No single month shows an extreme residual relative to the model's typical error.
A24: Multicollinearity | B24: No material concern | C24: Marketing spend and calls correlation is 0.30.
A25: Validation | B25: Use with caution | C25: Only 6 future months are held out; RMSE is $2346 and MAPE 1.4%.
A26: Data leakage - selected model | B26: No material concern | C26: The selected model excludes the month-end adjustment.
A27: Data leakage - rejected model | B27: Material concern | C27: Including the month-end adjustment produces holdout RMSE $265 but is unavailable at planning time.
A29: Model | B29: R-squared | C29: Typical Error / Holdout RMSE | D29: Planning Suitability
A30: Selected pre-month-end model | B30: 0.98830922 | C30: 2345.684 | D30: Usable with caution
A31: Leaked month-end model | B31: 0.99990722 | C31: 265.20855 | D31: Reject for planning
A33: Coefficient | B33: Selected Model | C33: Leaked Model | D33: Comment
A34: Intercept | B34: 47583.866 | C34: 7981.4433 | D34: Baseline
A35: Marketing Spend | B35: 3.1871276 | C35: 0.47320802 | D35: Pre-month-end input
A36: Pre-Month-End Calls | B36: 626.51935 | C36: 101.06383 | D36: Pre-month-end input
A37: Month-End Adjustment | B37: Excluded | C37: 5.2639226 | D37: Leaked; reject from planning
A39: Month | B39: Marketing Spend | C39: Pre-Month-End Calls | D39: Actual Sales | E39: Selected Prediction | F39: Residual | G39: Holdout Prediction | H39: Period Role
A40: 45292 | B40: 14000 | C40: 45 | D40: 117100 | E40: 120397.02 | F40: -3297.0225 | H40: Training
A41: 45323 | B41: 16200 | C41: 52 | D41: 134560 | E41: 131794.34 | F41: 2765.6614 | H41: Training
A42: 45352 | B42: 18400 | C42: 59 | D42: 142020 | E42: 143191.65 | F42: -1171.6547 | H42: Training
A43: 45383 | B43: 20600 | C43: 66 | D43: 157680 | E43: 154588.97 | F43: 3091.0292 | H43: Training
A44: 45413 | B44: 22800 | C44: 73 | D44: 165040 | E44: 165986.29 | F44: -946.28696 | H44: Training
A45: 45444 | B45: 25000 | C45: 80 | D45: 178400 | E45: 177383.6 | F45: 1016.3969 | H45: Training
A46: 45474 | B46: 27200 | C46: 87 | D46: 184060 | E46: 188780.92 | F46: -4720.9192 | H46: Training
A47: 45505 | B47: 29400 | C47: 94 | D47: 201520 | E47: 200178.24 | F47: 1341.7647 | H47: Training
A48: 45536 | B48: 14000 | C48: 101 | D48: 154420 | E48: 155482.11 | F48: -1062.1061 | H48: Training
A49: 45566 | B49: 16200 | C49: 45 | D49: 131020 | E49: 127408.7 | F49: 3611.2968 | H49: Training
A50: 45597 | B50: 18400 | C50: 52 | D50: 138380 | E50: 138806.02 | F50: -426.01928 | H50: Training
A51: 45627 | B51: 20600 | C51: 59 | D51: 151740 | E51: 150203.34 | F51: 1536.6646 | H51: Training
... A57: 45809 | B57: 16200 | C57: 101 | D57: 164140 | E57: 162493.79 | F57: 1646.2133 | H57: Training
A58: 45839 | B58: 18400 | C58: 45 | D58: 130740 | E58: 134420.38 | F58: -3680.3838 | G58: 134758.44 | H58: Holdout
A59: 45870 | B59: 20600 | C59: 52 | D59: 148200 | E59: 145817.7 | F59: 2382.3001 | G59: 146052.68 | H59: Holdout
A60: 45901 | B60: 22800 | C60: 59 | D60: 155660 | E60: 157215.02 | F60: -1555.0161 | G60: 157346.92 | H60: Holdout
A61: 45931 | B61: 25000 | C61: 66 | D61: 171320 | E61: 168612.33 | F61: 2707.6678 | G61: 168641.16 | H61: Holdout
A62: 45962 | B62: 27200 | C62: 73 | D62: 178680 | E62: 180009.65 | F62: -1329.6483 | G62: 179935.41 | H62: Holdout
A63: 45992 | B63: 29400 | C63: 80 | D63: 192040 | E63: 191406.96 | F63: 633.03558 | G63: 191229.65 | H63: Holdout
